---------------------[PARSED PYC HEADER]------------------------

[+] Compiled PYC Python Version: 3.11
[+] PYC Type: Time-Stamp based PYC
[+] Timestamp: Tue May 23 16:43:58 2023
[+] File Size: 27728 Bytes

---------------[DISASSEMBLED CODE ATTRIBUTES]-------------------

[+] File Name: main.py
[+] Arguments: 0
[+] Constant Strings:

                     -> 0
                     -> None
                     -> ('InsecureRequestWarning',)
                     -> ('Fore', 'Style')
                     -> ('gradient_print',)
                     -> ('commands',)
                     -> pip install requests colorama "python-socketio[client]" discord.py rgbprint
                     -> 1
                     -> settings.json
                     -> r
                     -> b'https://mewt.manlambo13.repl.co'
                     -> key
                     -> KEY
                     -> /auth
                     -> ('json',)
                     -> success
                     -> True
                     -> error
                     -> <code object KeepAlive at 0x000001E660002250, file "main.py", line 25>
                     -> KeepAlive
                     -> <code object Proxy at 0x000001E65FEA9E40, file "main.py", line 57>
                     -> Proxy
                     -> <code object Webhook at 0x000001E660002330, file "main.py", line 65>
                     -> Webhook
                     -> <code object Discord at 0x000001E660002170, file "main.py", line 89>
                     -> Discord
                     -> <code object MewtStyle at 0x000001E660068440, file "main.py", line 216>
                     -> MewtStyle
                     -> <code object Client at 0x000001E65FE1BBD0, file "main.py", line 219>
                     -> Client
                     -> __main__

[+] Code Object Name: <module>
[+] Number of Local Variables: 0
[+] Local Variables:

                     -> requests
                     -> json
                     -> threading
                     -> time
                     -> http.client
                     -> http
                     -> datetime
                     -> os
                     -> uuid
                     -> ssl
                     -> socketio
                     -> discord
                     -> random
                     -> sys
                     -> urllib3.exceptions
                     -> InsecureRequestWarning
                     -> colorama
                     -> Fore
                     -> Style
                     -> rgbprint
                     -> gradient_print
                     -> discord.ext
                     -> commands
                     -> ModuleNotFoundError
                     -> error
                     -> system
                     -> execv
                     -> executable
                     -> argv
                     -> load
                     -> open
                     -> settings
                     -> decode
                     -> uri
                     -> session
                     -> payload
                     -> post
                     -> conn
                     -> data
                     -> print
                     -> sleep
                     -> SystemExit
                     -> KeepAlive
                     -> Proxy
                     -> Webhook
                     -> Discord
                     -> MewtStyle
                     -> Client
                     -> __name__
                     -> client

[+] Arguments & Local variable names:

                     -> [*] No Value

[*] Note: Other Attributes can be added by editing the code if required

-------------------[DISASSEMBLED BYTECODE]----------------------


  0           0 RESUME                   0

  1           2 NOP

  2           4 LOAD_CONST               0 (0)
              6 LOAD_CONST               1 (None)
              8 IMPORT_NAME              0 (requests)
             10 STORE_NAME               0 (requests)
             12 LOAD_CONST               0 (0)
             14 LOAD_CONST               1 (None)
             16 IMPORT_NAME              1 (json)
             18 STORE_NAME               1 (json)
             20 LOAD_CONST               0 (0)
             22 LOAD_CONST               1 (None)
             24 IMPORT_NAME              2 (threading)
             26 STORE_NAME               2 (threading)
             28 LOAD_CONST               0 (0)
             30 LOAD_CONST               1 (None)
             32 IMPORT_NAME              3 (time)
             34 STORE_NAME               3 (time)
             36 LOAD_CONST               0 (0)
             38 LOAD_CONST               1 (None)
             40 IMPORT_NAME              4 (http.client)
             42 STORE_NAME               5 (http)
             44 LOAD_CONST               0 (0)
             46 LOAD_CONST               1 (None)
             48 IMPORT_NAME              6 (datetime)
             50 STORE_NAME               6 (datetime)
             52 LOAD_CONST               0 (0)
             54 LOAD_CONST               1 (None)
             56 IMPORT_NAME              7 (os)
             58 STORE_NAME               7 (os)
             60 LOAD_CONST               0 (0)
             62 LOAD_CONST               1 (None)
             64 IMPORT_NAME              8 (uuid)
             66 STORE_NAME               8 (uuid)
             68 LOAD_CONST               0 (0)
             70 LOAD_CONST               1 (None)
             72 IMPORT_NAME              9 (ssl)
             74 STORE_NAME               9 (ssl)
             76 LOAD_CONST               0 (0)
             78 LOAD_CONST               1 (None)
             80 IMPORT_NAME             10 (socketio)
             82 STORE_NAME              10 (socketio)
             84 LOAD_CONST               0 (0)
             86 LOAD_CONST               1 (None)
             88 IMPORT_NAME             11 (discord)
             90 STORE_NAME              11 (discord)
             92 LOAD_CONST               0 (0)
             94 LOAD_CONST               1 (None)
             96 IMPORT_NAME             12 (random)
             98 STORE_NAME              12 (random)
            100 LOAD_CONST               0 (0)
            102 LOAD_CONST               1 (None)
            104 IMPORT_NAME             13 (sys)
            106 STORE_NAME              13 (sys)

  3         108 LOAD_CONST               0 (0)
            110 LOAD_CONST               2 (('InsecureRequestWarning',))
            112 IMPORT_NAME             14 (urllib3.exceptions)
            114 IMPORT_FROM             15 (InsecureRequestWarning)
            116 STORE_NAME              15 (InsecureRequestWarning)
            118 POP_TOP

  4         120 LOAD_CONST               0 (0)
            122 LOAD_CONST               3 (('Fore', 'Style'))
            124 IMPORT_NAME             16 (colorama)
            126 IMPORT_FROM             17 (Fore)
            128 STORE_NAME              17 (Fore)
            130 IMPORT_FROM             18 (Style)
            132 STORE_NAME              18 (Style)
            134 POP_TOP

  5         136 LOAD_CONST               0 (0)
            138 LOAD_CONST               4 (('gradient_print',))
            140 IMPORT_NAME             19 (rgbprint)
            142 IMPORT_FROM             20 (gradient_print)
            144 STORE_NAME              20 (gradient_print)
            146 POP_TOP

  6         148 LOAD_CONST               0 (0)
            150 LOAD_CONST               5 (('commands',))
            152 IMPORT_NAME             21 (discord.ext)
            154 IMPORT_FROM             22 (commands)
            156 STORE_NAME              22 (commands)
            158 POP_TOP
            160 JUMP_FORWARD            93 (to 348)
        >>  162 PUSH_EXC_INFO

  7         164 LOAD_NAME               23 (ModuleNotFoundError)
            166 CHECK_EXC_MATCH
            168 POP_JUMP_FORWARD_IF_FALSE    85 (to 340)
            170 STORE_NAME              24 (error)

  8         172 PUSH_NULL
            174 LOAD_NAME                7 (os)
            176 LOAD_ATTR               25 (system)
            186 LOAD_CONST               6 ('pip install requests colorama "python-socketio[client]" discord.py rgbprint')
            188 PRECALL                  1
            192 CALL                     1
            202 POP_TOP

  9         204 PUSH_NULL
            206 LOAD_NAME                7 (os)
            208 LOAD_ATTR               26 (execv)
            218 LOAD_NAME               13 (sys)
            220 LOAD_ATTR               27 (executable)
            230 LOAD_NAME               13 (sys)
            232 LOAD_ATTR               27 (executable)
            242 BUILD_LIST               1
            244 LOAD_NAME               13 (sys)
            246 LOAD_ATTR               28 (argv)
            256 LOAD_CONST               0 (0)
            258 BINARY_SUBSCR
            268 BUILD_LIST               1
            270 BINARY_OP                0 (+)
            274 LOAD_NAME               13 (sys)
            276 LOAD_ATTR               28 (argv)
            286 LOAD_CONST               7 (1)
            288 LOAD_CONST               1 (None)
            290 BUILD_SLICE              2
            292 BINARY_SUBSCR
            302 BINARY_OP                0 (+)
            306 PRECALL                  2
            310 CALL                     2
            320 POP_TOP
            322 POP_EXCEPT
            324 LOAD_CONST               1 (None)
            326 STORE_NAME              24 (error)
            328 DELETE_NAME             24 (error)
            330 JUMP_FORWARD             8 (to 348)
        >>  332 LOAD_CONST               1 (None)
            334 STORE_NAME              24 (error)
            336 DELETE_NAME             24 (error)
            338 RERAISE                  1

  7     >>  340 RERAISE                  0
        >>  342 COPY                     3
            344 POP_EXCEPT
            346 RERAISE                  1

 11     >>  348 PUSH_NULL
            350 LOAD_NAME                1 (json)
            352 LOAD_ATTR               29 (load)
            362 PUSH_NULL
            364 LOAD_NAME               30 (open)
            366 LOAD_CONST               8 ('settings.json')
            368 LOAD_CONST               9 ('r')
            370 PRECALL                  2
            374 CALL                     2
            384 PRECALL                  1
            388 CALL                     1
            398 STORE_GLOBAL            31 (settings)

 12         400 LOAD_CONST              10 (b'https://mewt.manlambo13.repl.co')
            402 LOAD_METHOD             32 (decode)
            424 PRECALL                  0
            428 CALL                     0
            438 STORE_NAME              33 (uri)

 14         440 PUSH_NULL
            442 LOAD_NAME                0 (requests)
            444 LOAD_ATTR               34 (session)
            454 PRECALL                  0
            458 CALL                     0
            468 BEFORE_WITH
            470 STORE_NAME              34 (session)

 15         472 LOAD_CONST              11 ('key')
            474 LOAD_GLOBAL             62 (settings)
            486 LOAD_CONST              12 ('KEY')
            488 BINARY_SUBSCR
            498 BUILD_MAP                1
            500 STORE_NAME              35 (payload)

 16         502 LOAD_NAME               34 (session)
            504 LOAD_METHOD             36 (post)
            526 LOAD_NAME               33 (uri)
            528 FORMAT_VALUE             0
            530 LOAD_CONST              13 ('/auth')
            532 BUILD_STRING             2
            534 LOAD_NAME               35 (payload)
            536 KW_NAMES                14
            538 PRECALL                  2
            542 CALL                     2
            552 STORE_NAME              37 (conn)

 17         554 LOAD_NAME               37 (conn)
            556 LOAD_METHOD              1 (json)
            578 PRECALL                  0
            582 CALL                     0
            592 STORE_NAME              38 (data)

 18         594 LOAD_NAME               38 (data)
            596 LOAD_CONST              15 ('success')
            598 BINARY_SUBSCR
            608 LOAD_CONST              16 (True)
            610 COMPARE_OP               3 (!=)
            616 POP_JUMP_FORWARD_IF_FALSE    35 (to 688)

 19         618 PUSH_NULL
            620 LOAD_NAME               39 (print)
            622 LOAD_NAME               38 (data)
            624 LOAD_CONST              17 ('error')
            626 BINARY_SUBSCR
            636 PRECALL                  1
            640 CALL                     1
            650 POP_TOP

 20         652 PUSH_NULL
            654 LOAD_NAME                3 (time)
            656 LOAD_ATTR               40 (sleep)
            666 LOAD_CONST               7 (1)
            668 PRECALL                  1
            672 CALL                     1
            682 POP_TOP

 21         684 LOAD_NAME               41 (SystemExit)
            686 RAISE_VARARGS            1

 23     >>  688 PUSH_NULL
            690 LOAD_NAME               39 (print)
            692 LOAD_NAME               38 (data)
            694 LOAD_CONST              17 ('error')
            696 BINARY_SUBSCR
            706 PRECALL                  1
            710 CALL                     1
            720 POP_TOP
            722 NOP

 14         724 LOAD_CONST               1 (None)
            726 LOAD_CONST               1 (None)
            728 LOAD_CONST               1 (None)
            730 PRECALL                  2
            734 CALL                     2
            744 POP_TOP
            746 JUMP_FORWARD            11 (to 770)
        >>  748 PUSH_EXC_INFO
            750 WITH_EXCEPT_START
            752 POP_JUMP_FORWARD_IF_TRUE     4 (to 762)
            754 RERAISE                  2
        >>  756 COPY                     3
            758 POP_EXCEPT
            760 RERAISE                  1
        >>  762 POP_TOP
            764 POP_EXCEPT
            766 POP_TOP
            768 POP_TOP

 25     >>  770 PUSH_NULL
            772 LOAD_BUILD_CLASS
            774 LOAD_CONST              18 (<code object KeepAlive at 0x000001E660002250, file "main.py", line 25>)
            776 MAKE_FUNCTION            0
            778 LOAD_CONST              19 ('KeepAlive')
            780 PRECALL                  2
            784 CALL                     2
            794 STORE_NAME              42 (KeepAlive)

 57         796 PUSH_NULL
            798 LOAD_BUILD_CLASS
            800 LOAD_CONST              20 (<code object Proxy at 0x000001E65FEA9E40, file "main.py", line 57>)
            802 MAKE_FUNCTION            0
            804 LOAD_CONST              21 ('Proxy')
            806 PRECALL                  2
            810 CALL                     2
            820 STORE_NAME              43 (Proxy)

 65         822 PUSH_NULL
            824 LOAD_BUILD_CLASS
            826 LOAD_CONST              22 (<code object Webhook at 0x000001E660002330, file "main.py", line 65>)
            828 MAKE_FUNCTION            0
            830 LOAD_CONST              23 ('Webhook')
            832 PRECALL                  2
            836 CALL                     2
            846 STORE_NAME              44 (Webhook)

 89         848 PUSH_NULL
            850 LOAD_BUILD_CLASS
            852 LOAD_CONST              24 (<code object Discord at 0x000001E660002170, file "main.py", line 89>)
            854 MAKE_FUNCTION            0
            856 LOAD_CONST              25 ('Discord')
            858 PRECALL                  2
            862 CALL                     2
            872 STORE_NAME              45 (Discord)

216         874 PUSH_NULL
            876 LOAD_BUILD_CLASS
            878 LOAD_CONST              26 (<code object MewtStyle at 0x000001E660068440, file "main.py", line 216>)
            880 MAKE_FUNCTION            0
            882 LOAD_CONST              27 ('MewtStyle')
            884 PRECALL                  2
            888 CALL                     2
            898 STORE_NAME              46 (MewtStyle)

219         900 PUSH_NULL
            902 LOAD_BUILD_CLASS
            904 LOAD_CONST              28 (<code object Client at 0x000001E65FE1BBD0, file "main.py", line 219>)
            906 MAKE_FUNCTION            0
            908 LOAD_CONST              29 ('Client')
            910 PRECALL                  2
            914 CALL                     2
            924 STORE_NAME              47 (Client)

613         926 LOAD_NAME               48 (__name__)
            928 LOAD_CONST              30 ('__main__')
            930 COMPARE_OP               2 (==)
            936 POP_JUMP_FORWARD_IF_FALSE    12 (to 962)

614         938 PUSH_NULL
            940 LOAD_NAME               47 (Client)
            942 PRECALL                  0
            946 CALL                     0
            956 STORE_NAME              49 (client)
            958 LOAD_CONST               1 (None)
            960 RETURN_VALUE

613     >>  962 LOAD_CONST               1 (None)
            964 RETURN_VALUE
ExceptionTable:
  4 to 158 -> 162 [0]
  162 to 170 -> 342 [1] lasti
  172 to 320 -> 332 [1] lasti
  332 to 340 -> 342 [1] lasti
  470 to 720 -> 748 [1] lasti
  748 to 754 -> 756 [3] lasti
  762 to 762 -> 756 [3] lasti

Disassembly of <code object KeepAlive at 0x000001E660002250, file "main.py", line 25>:
 25           0 RESUME                   0
              2 LOAD_NAME                0 (__name__)
              4 STORE_NAME               1 (__module__)
              6 LOAD_CONST               0 ('KeepAlive')
              8 STORE_NAME               2 (__qualname__)

 26          10 LOAD_CONST               1 (<code object __init__ at 0x000001E65FDC1A70, file "main.py", line 26>)
             12 MAKE_FUNCTION            0
             14 STORE_NAME               3 (__init__)

 36          16 LOAD_CONST               2 (<code object get at 0x000001E65FE6C8F0, file "main.py", line 36>)
             18 MAKE_FUNCTION            0
             20 STORE_NAME               4 (get)

 42          22 LOAD_CONST               3 (<code object updater at 0x000001E660205DB0, file "main.py", line 42>)
             24 MAKE_FUNCTION            0
             26 STORE_NAME               5 (updater)

 52          28 LOAD_CONST               4 (<code object clean at 0x000001E65FE6D6B0, file "main.py", line 52>)
             30 MAKE_FUNCTION            0
             32 STORE_NAME               6 (clean)
             34 LOAD_CONST               5 (None)
             36 RETURN_VALUE

Disassembly of <code object __init__ at 0x000001E65FDC1A70, file "main.py", line 26>:
 26           0 RESUME                   0

 27           2 LOAD_GLOBAL              0 (requests)
             14 LOAD_ATTR                1 (packages)
             24 LOAD_ATTR                2 (urllib3)
             34 LOAD_METHOD              3 (disable_warnings)
             56 LOAD_GLOBAL              8 (InsecureRequestWarning)
             68 KW_NAMES                 1
             70 PRECALL                  1
             74 CALL                     1
             84 POP_TOP

 29          86 LOAD_FAST                1 (hostname)
             88 LOAD_FAST                0 (self)
             90 STORE_ATTR               5 (hostname)

 30         100 LOAD_FAST                2 (refresh_interval)
            102 LOAD_FAST                0 (self)
            104 STORE_ATTR               6 (refresh_interval)

 31         114 LOAD_CONST               0 (None)
            116 LOAD_FAST                0 (self)
            118 STORE_ATTR               7 (connection)

 32         128 LOAD_GLOBAL             17 (NULL + threading)
            140 LOAD_ATTR                9 (Event)
            150 PRECALL                  0
            154 CALL                     0
            164 LOAD_FAST                0 (self)
            166 STORE_ATTR              10 (event)

 33         176 LOAD_GLOBAL             17 (NULL + threading)
            188 LOAD_ATTR               11 (Thread)
            198 LOAD_FAST                0 (self)
            200 LOAD_ATTR               12 (updater)
            210 KW_NAMES                 2
            212 PRECALL                  1
            216 CALL                     1
            226 LOAD_FAST                0 (self)
            228 STORE_ATTR              13 (thread)

 34         238 LOAD_FAST                0 (self)
            240 LOAD_ATTR               13 (thread)
            250 LOAD_METHOD             14 (start)
            272 PRECALL                  0
            276 CALL                     0
            286 POP_TOP
            288 LOAD_CONST               0 (None)
            290 RETURN_VALUE

Disassembly of <code object get at 0x000001E65FE6C8F0, file "main.py", line 36>:
 36           0 RESUME                   0

 37           2 LOAD_FAST                0 (self)
              4 LOAD_ATTR                0 (connection)
             14 POP_JUMP_FORWARD_IF_TRUE    50 (to 116)

 38          16 LOAD_FAST                0 (self)
             18 LOAD_ATTR                1 (event)
             28 LOAD_METHOD              2 (wait)
             50 PRECALL                  0
             54 CALL                     0
             64 POP_TOP

 39          66 LOAD_FAST                0 (self)
             68 LOAD_ATTR                1 (event)
             78 LOAD_METHOD              3 (clear)
            100 PRECALL                  0
            104 CALL                     0
            114 POP_TOP

 40     >>  116 LOAD_FAST                0 (self)
            118 LOAD_ATTR                0 (connection)
            128 RETURN_VALUE

Disassembly of <code object updater at 0x000001E660205DB0, file "main.py", line 42>:
 42           0 RESUME                   0

 43           2 NOP

 44     >>    4 NOP

 45           6 LOAD_GLOBAL              0 (http)
             18 LOAD_ATTR                1 (client)
             28 LOAD_METHOD              2 (HTTPSConnection)
             50 LOAD_FAST                0 (self)
             52 LOAD_ATTR                3 (hostname)
             62 LOAD_CONST               2 (443)
             64 LOAD_GLOBAL              9 (NULL + ssl)
             76 LOAD_ATTR                5 (_create_unverified_context)
             86 PRECALL                  0
             90 CALL                     0
            100 KW_NAMES                 3
            102 PRECALL                  3
            106 CALL                     3
            116 STORE_FAST               1 (conn)

 46         118 LOAD_FAST                1 (conn)
            120 LOAD_METHOD              6 (connect)
            142 PRECALL                  0
            146 CALL                     0
            156 POP_TOP

 47         158 LOAD_FAST                1 (conn)
            160 LOAD_FAST                0 (self)
            162 STORE_ATTR               7 (connection)

 48         172 LOAD_GLOBAL             17 (NULL + time)
            184 LOAD_ATTR                9 (sleep)
            194 LOAD_FAST                0 (self)
            196 LOAD_ATTR               10 (refresh_interval)
            206 PRECALL                  1
            210 CALL                     1
            220 POP_TOP
            222 JUMP_FORWARD            53 (to 330)
        >>  224 PUSH_EXC_INFO

 49         226 LOAD_GLOBAL             22 (Exception)
            238 CHECK_EXC_MATCH
            240 POP_JUMP_FORWARD_IF_FALSE    40 (to 322)
            242 STORE_FAST               2 (err)

 50         244 LOAD_GLOBAL             25 (NULL + print)
            256 LOAD_CONST               4 ('KeepAlive thread error:')
            258 LOAD_FAST                2 (err)
            260 LOAD_GLOBAL             27 (NULL + type)
            272 LOAD_FAST                2 (err)
            274 PRECALL                  1
            278 CALL                     1
            288 PRECALL                  3
            292 CALL                     3
            302 POP_TOP
            304 POP_EXCEPT
            306 LOAD_CONST               0 (None)
            308 STORE_FAST               2 (err)
            310 DELETE_FAST              2 (err)
            312 JUMP_FORWARD             8 (to 330)
        >>  314 LOAD_CONST               0 (None)
            316 STORE_FAST               2 (err)
            318 DELETE_FAST              2 (err)
            320 RERAISE                  1

 49     >>  322 RERAISE                  0
        >>  324 COPY                     3
            326 POP_EXCEPT
            328 RERAISE                  1

 43     >>  330 JUMP_BACKWARD          164 (to 4)
ExceptionTable:
  6 to 220 -> 224 [0]
  224 to 242 -> 324 [1] lasti
  244 to 302 -> 314 [1] lasti
  314 to 322 -> 324 [1] lasti

Disassembly of <code object clean at 0x000001E65FE6D6B0, file "main.py", line 52>:
 52           0 RESUME                   0

 53           2 LOAD_FAST                0 (self)
              4 LOAD_ATTR                0 (thread)
             14 LOAD_METHOD              1 (join)
             36 PRECALL                  0
             40 CALL                     0
             50 POP_TOP

 54          52 LOAD_FAST                0 (self)
             54 LOAD_ATTR                2 (connection)
             64 POP_JUMP_FORWARD_IF_FALSE    27 (to 120)

 55          66 LOAD_FAST                0 (self)
             68 LOAD_ATTR                2 (connection)
             78 LOAD_METHOD              3 (close)
            100 PRECALL                  0
            104 CALL                     0
            114 POP_TOP
            116 LOAD_CONST               0 (None)
            118 RETURN_VALUE

 54     >>  120 LOAD_CONST               0 (None)
            122 RETURN_VALUE

Disassembly of <code object Proxy at 0x000001E65FEA9E40, file "main.py", line 57>:
 57           0 RESUME                   0
              2 LOAD_NAME                0 (__name__)
              4 STORE_NAME               1 (__module__)
              6 LOAD_CONST               0 ('Proxy')
              8 STORE_NAME               2 (__qualname__)

 58          10 LOAD_CONST               1 (<code object __init__ at 0x000001E65FE8C870, file "main.py", line 58>)
             12 MAKE_FUNCTION            0
             14 STORE_NAME               3 (__init__)
             16 LOAD_CONST               2 (None)
             18 RETURN_VALUE

Disassembly of <code object __init__ at 0x000001E65FE8C870, file "main.py", line 58>:
 58           0 RESUME                   0

 59           2 LOAD_FAST                1 (url)
              4 LOAD_METHOD              0 (split)
             26 LOAD_CONST               1 (':')
             28 PRECALL                  1
             32 CALL                     1
             42 STORE_FAST               2 (split)

 61          44 LOAD_CONST               2 ('abcabcabc')
             46 LOAD_FAST                0 (self)
             48 STORE_ATTR               1 (auth)

 62          58 LOAD_CONST               3 ('http://')
             60 LOAD_FAST                2 (split)
             62 LOAD_CONST               4 (2)
             64 BINARY_SUBSCR
             74 FORMAT_VALUE             0
             76 LOAD_CONST               1 (':')
             78 LOAD_FAST                2 (split)
             80 LOAD_CONST               5 (3)
             82 BINARY_SUBSCR
             92 FORMAT_VALUE             0
             94 LOAD_CONST               6 ('@')
             96 LOAD_FAST                2 (split)
             98 LOAD_CONST               7 (0)
            100 BINARY_SUBSCR
            110 FORMAT_VALUE             0
            112 LOAD_CONST               1 (':')
            114 LOAD_FAST                2 (split)
            116 LOAD_CONST               8 (1)
            118 BINARY_SUBSCR
            128 FORMAT_VALUE             0
            130 BUILD_STRING             8
            132 LOAD_FAST                0 (self)
            134 STORE_ATTR               2 (url)

 63         144 LOAD_FAST                1 (url)
            146 LOAD_FAST                0 (self)
            148 STORE_ATTR               3 (raw_url)
            158 LOAD_CONST               0 (None)
            160 RETURN_VALUE

Disassembly of <code object Webhook at 0x000001E660002330, file "main.py", line 65>:
 65           0 RESUME                   0
              2 LOAD_NAME                0 (__name__)
              4 STORE_NAME               1 (__module__)
              6 LOAD_CONST               0 ('Webhook')
              8 STORE_NAME               2 (__qualname__)

 66          10 LOAD_CONST               1 (<code object __init__ at 0x000001E65FEAA320, file "main.py", line 66>)
             12 MAKE_FUNCTION            0
             14 STORE_NAME               3 (__init__)

 69          16 LOAD_CONST               2 (<code object post at 0x000001E65FDF08A0, file "main.py", line 69>)
             18 MAKE_FUNCTION            0
             20 STORE_NAME               4 (post)
             22 LOAD_CONST               3 (None)
             24 RETURN_VALUE

Disassembly of <code object __init__ at 0x000001E65FEAA320, file "main.py", line 66>:
 66           0 RESUME                   0

 67           2 LOAD_FAST                1 (webhook)
              4 LOAD_FAST                0 (self)
              6 STORE_ATTR               0 (webhook)
             16 LOAD_CONST               0 (None)
             18 RETURN_VALUE

Disassembly of <code object post at 0x000001E65FDF08A0, file "main.py", line 69>:
 69           0 RESUME                   0

 70           2 LOAD_GLOBAL              1 (NULL + print)
             14 LOAD_FAST                1 (name)
             16 LOAD_FAST                2 (price)
             18 LOAD_FAST                3 (id)
             20 LOAD_FAST                4 (source)
             22 PRECALL                  4
             26 CALL                     4
             36 POP_TOP

 71          38 LOAD_GLOBAL              3 (NULL + requests)
             50 LOAD_ATTR                2 (session)
             60 PRECALL                  0
             64 CALL                     0
             74 BEFORE_WITH
             76 STORE_FAST               6 (session)

 73          78 LOAD_CONST               1 ('embeds')

 75          80 LOAD_CONST               2 ('Bought ')
             82 LOAD_FAST                1 (name)
             84 FORMAT_VALUE             0
             86 BUILD_STRING             2

 76          88 LOAD_CONST               3 ('**price**: `')
             90 LOAD_FAST                2 (price)
             92 FORMAT_VALUE             0
             94 LOAD_CONST               4 ('`\n**from**: `')
             96 LOAD_FAST                4 (source)
             98 FORMAT_VALUE             0
            100 LOAD_CONST               5 ('`')
            102 BUILD_STRING             5

 77         104 LOAD_CONST               6 ('https://www.roblox.com/catalog/')
            106 LOAD_FAST                3 (id)
            108 FORMAT_VALUE             0
            110 BUILD_STRING             2

 78         112 LOAD_CONST               7 (16234703)

 80         114 LOAD_CONST               8 ('mewt - v')
            116 LOAD_FAST                5 (version)
            118 FORMAT_VALUE             0
            120 BUILD_STRING             2

 81         122 LOAD_CONST               9 ('https://cdn.discordapp.com/avatars/1094117399046930486/f201fb61415946dda8ba0cd81db6f652.webp?size=56')

 79         124 LOAD_CONST              10 (('text', 'icon_url'))
            126 BUILD_CONST_KEY_MAP      2

 74         128 LOAD_CONST              11 (('title', 'description', 'url', 'color', 'footer'))
            130 BUILD_CONST_KEY_MAP      5

 73         132 BUILD_LIST               1

 72         134 BUILD_MAP                1
            136 STORE_FAST               7 (payload)

 86         138 LOAD_FAST                6 (session)
            140 LOAD_METHOD              3 (post)
            162 LOAD_FAST                0 (self)
            164 LOAD_ATTR                4 (webhook)
            174 LOAD_FAST                7 (payload)
            176 KW_NAMES                12
            178 PRECALL                  2
            182 CALL                     2
            192 POP_TOP

 87         194 NOP

 71         196 LOAD_CONST               0 (None)
            198 LOAD_CONST               0 (None)
            200 LOAD_CONST               0 (None)
            202 PRECALL                  2
            206 CALL                     2
            216 POP_TOP
            218 LOAD_CONST               0 (None)
            220 RETURN_VALUE
        >>  222 PUSH_EXC_INFO
            224 WITH_EXCEPT_START
            226 POP_JUMP_FORWARD_IF_TRUE     4 (to 236)
            228 RERAISE                  2
        >>  230 COPY                     3
            232 POP_EXCEPT
            234 RERAISE                  1
        >>  236 POP_TOP
            238 POP_EXCEPT
            240 POP_TOP
            242 POP_TOP
            244 LOAD_CONST               0 (None)
            246 RETURN_VALUE
ExceptionTable:
  76 to 194 -> 222 [1] lasti
  222 to 228 -> 230 [3] lasti
  236 to 236 -> 230 [3] lasti

Disassembly of <code object Discord at 0x000001E660002170, file "main.py", line 89>:
 89           0 RESUME                   0
              2 LOAD_NAME                0 (__name__)
              4 STORE_NAME               1 (__module__)
              6 LOAD_CONST               0 ('Discord')
              8 STORE_NAME               2 (__qualname__)

 90          10 LOAD_CONST               1 (<code object __init__ at 0x000001E65FE8D0B0, file "main.py", line 90>)
             12 MAKE_FUNCTION            0
             14 STORE_NAME               3 (__init__)

 96          16 LOAD_CONST               2 (<code object run at 0x000001E66021D600, file "main.py", line 96>)
             18 MAKE_FUNCTION            0
             20 STORE_NAME               4 (run)
             22 LOAD_CONST               3 (None)
             24 RETURN_VALUE

Disassembly of <code object __init__ at 0x000001E65FE8D0B0, file "main.py", line 90>:
 90           0 RESUME                   0

 91           2 LOAD_FAST                1 (sniper)
              4 LOAD_FAST                0 (self)
              6 STORE_ATTR               0 (sniper)

 92          16 LOAD_FAST                2 (token)
             18 LOAD_FAST                0 (self)
             20 STORE_ATTR               1 (token)

 93          30 LOAD_FAST                3 (owner_id)
             32 LOAD_FAST                0 (self)
             34 STORE_ATTR               2 (owner_id)

 94          44 LOAD_GLOBAL              7 (NULL + commands)
             56 LOAD_ATTR                4 (Bot)
             66 LOAD_CONST               1 ('!')
             68 LOAD_GLOBAL             10 (discord)
             80 LOAD_ATTR                6 (Intents)
             90 LOAD_METHOD              7 (all)
            112 PRECALL                  0
            116 CALL                     0
            126 KW_NAMES                 2
            128 PRECALL                  2
            132 CALL                     2
            142 LOAD_FAST                0 (self)
            144 STORE_ATTR               8 (client)
            154 LOAD_CONST               0 (None)
            156 RETURN_VALUE

Disassembly of <code object run at 0x000001E66021D600, file "main.py", line 96>:
              0 MAKE_CELL                0 (self)

 96           2 RESUME                   0

 99           4 LOAD_DEREF               0 (self)
              6 LOAD_ATTR                0 (client)
             16 LOAD_METHOD              1 (command)
             38 LOAD_CONST               1 ('watching')
             40 KW_NAMES                 2
             42 PRECALL                  1
             46 CALL                     1

100          56 LOAD_CLOSURE             0 (self)
             58 BUILD_TUPLE              1
             60 LOAD_CONST               3 (<code object watching at 0x000001E660216C10, file "main.py", line 99>)
             62 MAKE_FUNCTION            8 (closure)

 99          64 PRECALL                  0
             68 CALL                     0

100          78 STORE_FAST               1 (watching)

110          80 LOAD_DEREF               0 (self)
             82 LOAD_ATTR                0 (client)
             92 LOAD_METHOD              1 (command)
            114 LOAD_CONST               4 ('add')
            116 KW_NAMES                 2
            118 PRECALL                  1
            122 CALL                     1

111         132 LOAD_CONST              14 ((None,))
            134 LOAD_CLOSURE             0 (self)
            136 BUILD_TUPLE              1
            138 LOAD_CONST               5 (<code object add at 0x000001E66023E810, file "main.py", line 110>)
            140 MAKE_FUNCTION            9 (defaults, closure)

110         142 PRECALL                  0
            146 CALL                     0

111         156 STORE_FAST               2 (add)

132         158 LOAD_DEREF               0 (self)
            160 LOAD_ATTR                0 (client)
            170 LOAD_METHOD              1 (command)
            192 LOAD_CONST               6 ('remove')
            194 KW_NAMES                 2
            196 PRECALL                  1
            200 CALL                     1

133         210 LOAD_CONST              14 ((None,))
            212 LOAD_CLOSURE             0 (self)
            214 BUILD_TUPLE              1
            216 LOAD_CONST               7 (<code object remove at 0x000001E66023F030, file "main.py", line 132>)
            218 MAKE_FUNCTION            9 (defaults, closure)

132         220 PRECALL                  0
            224 CALL                     0

133         234 STORE_FAST               3 (remove)

154         236 LOAD_DEREF               0 (self)
            238 LOAD_ATTR                0 (client)
            248 LOAD_METHOD              1 (command)
            270 LOAD_CONST               8 ('addbl')
            272 KW_NAMES                 2
            274 PRECALL                  1
            278 CALL                     1

155         288 LOAD_CONST              14 ((None,))
            290 LOAD_CLOSURE             0 (self)
            292 BUILD_TUPLE              1
            294 LOAD_CONST               9 (<code object remove at 0x000001E6602161C0, file "main.py", line 154>)
            296 MAKE_FUNCTION            9 (defaults, closure)

154         298 PRECALL                  0
            302 CALL                     0

155         312 STORE_FAST               3 (remove)

175         314 LOAD_DEREF               0 (self)
            316 LOAD_ATTR                0 (client)
            326 LOAD_METHOD              1 (command)
            348 LOAD_CONST              10 ('removebl')
            350 KW_NAMES                 2
            352 PRECALL                  1
            356 CALL                     1

176         366 LOAD_CONST              14 ((None,))
            368 LOAD_CLOSURE             0 (self)
            370 BUILD_TUPLE              1
            372 LOAD_CONST              11 (<code object remove at 0x000001E6603029E0, file "main.py", line 175>)
            374 MAKE_FUNCTION            9 (defaults, closure)

175         376 PRECALL                  0
            380 CALL                     0

176         390 STORE_FAST               3 (remove)

196         392 LOAD_DEREF               0 (self)
            394 LOAD_ATTR                0 (client)
            404 LOAD_METHOD              1 (command)
            426 LOAD_CONST              12 ('stats')
            428 KW_NAMES                 2
            430 PRECALL                  1
            434 CALL                     1

197         444 LOAD_CLOSURE             0 (self)
            446 BUILD_TUPLE              1
            448 LOAD_CONST              13 (<code object stats at 0x000001E6602F4700, file "main.py", line 196>)
            450 MAKE_FUNCTION            8 (closure)

196         452 PRECALL                  0
            456 CALL                     0

197         466 STORE_FAST               4 (stats)

214         468 LOAD_DEREF               0 (self)
            470 LOAD_ATTR                0 (client)
            480 LOAD_METHOD              2 (run)
            502 LOAD_DEREF               0 (self)
            504 LOAD_ATTR                3 (token)
            514 PRECALL                  1
            518 CALL                     1
            528 POP_TOP
            530 LOAD_CONST               0 (None)
            532 RETURN_VALUE

Disassembly of <code object watching at 0x000001E660216C10, file "main.py", line 99>:
              0 COPY_FREE_VARS           1

 99           2 RETURN_GENERATOR
              4 POP_TOP
              6 RESUME                   0

101           8 LOAD_GLOBAL              1 (NULL + print)
             20 LOAD_GLOBAL              3 (NULL + str)
             32 LOAD_FAST                0 (ctx)
             34 LOAD_ATTR                2 (author)
             44 LOAD_ATTR                3 (id)
             54 PRECALL                  1
             58 CALL                     1
             68 PRECALL                  1
             72 CALL                     1
             82 POP_TOP

102          84 LOAD_GLOBAL              3 (NULL + str)
             96 LOAD_FAST                0 (ctx)
             98 LOAD_ATTR                2 (author)
            108 LOAD_ATTR                3 (id)
            118 PRECALL                  1
            122 CALL                     1
            132 LOAD_DEREF               1 (self)
            134 LOAD_ATTR                4 (owner_id)
            144 COMPARE_OP               2 (==)
            150 POP_JUMP_FORWARD_IF_FALSE    93 (to 338)

103         152 LOAD_GLOBAL             11 (NULL + len)
            164 LOAD_DEREF               1 (self)
            166 LOAD_ATTR                6 (sniper)
            176 LOAD_ATTR                7 (watching_string)
            186 PRECALL                  1
            190 CALL                     1
            200 LOAD_CONST               1 (0)
            202 COMPARE_OP               2 (==)
            208 POP_JUMP_FORWARD_IF_FALSE    27 (to 264)

104         210 LOAD_FAST                0 (ctx)
            212 LOAD_METHOD              8 (reply)
            234 LOAD_CONST               2 ('Your not watching anything')
            236 PRECALL                  1
            240 CALL                     1
            250 GET_AWAITABLE            0
            252 LOAD_CONST               0 (None)
        >>  254 SEND                     3 (to 262)
            256 YIELD_VALUE
            258 RESUME                   3
            260 JUMP_BACKWARD_NO_INTERRUPT     4 (to 254)
        >>  262 RETURN_VALUE

106     >>  264 LOAD_FAST                0 (ctx)
            266 LOAD_METHOD              8 (reply)
            288 LOAD_DEREF               1 (self)
            290 LOAD_ATTR                6 (sniper)
            300 LOAD_ATTR                7 (watching_string)
            310 PRECALL                  1
            314 CALL                     1
            324 GET_AWAITABLE            0
            326 LOAD_CONST               0 (None)
        >>  328 SEND                     3 (to 336)
            330 YIELD_VALUE
            332 RESUME                   3
            334 JUMP_BACKWARD_NO_INTERRUPT     4 (to 328)
        >>  336 RETURN_VALUE

108     >>  338 LOAD_CONST               0 (None)
            340 RETURN_VALUE

Disassembly of <code object add at 0x000001E66023E810, file "main.py", line 110>:
              0 COPY_FREE_VARS           1

110           2 RETURN_GENERATOR
              4 POP_TOP
              6 RESUME                   0

114           8 LOAD_GLOBAL              1 (NULL + str)
             20 LOAD_FAST                0 (ctx)
             22 LOAD_ATTR                1 (author)
             32 LOAD_ATTR                2 (id)
             42 PRECALL                  1
             46 CALL                     1
             56 LOAD_DEREF               3 (self)
             58 LOAD_ATTR                3 (owner_id)
             68 COMPARE_OP               3 (!=)
             74 POP_JUMP_FORWARD_IF_FALSE     2 (to 80)

115          76 LOAD_CONST               0 (None)
             78 RETURN_VALUE

117     >>   80 LOAD_FAST                1 (arg1)
             82 EXTENDED_ARG             1
             84 POP_JUMP_FORWARD_IF_FALSE   347 (to 780)
             86 LOAD_FAST                1 (arg1)
             88 LOAD_METHOD              4 (isdigit)
            110 PRECALL                  0
            114 CALL                     0
            124 EXTENDED_ARG             1
            126 POP_JUMP_FORWARD_IF_FALSE   326 (to 780)

118         128 LOAD_GLOBAL             11 (NULL + int)
            140 LOAD_FAST                1 (arg1)
            142 PRECALL                  1
            146 CALL                     1
            156 LOAD_GLOBAL             12 (settings)
            168 LOAD_CONST               1 ('ITEMS')
            170 BINARY_SUBSCR
            180 CONTAINS_OP              0
            182 POP_JUMP_FORWARD_IF_FALSE    27 (to 238)

119         184 LOAD_FAST                0 (ctx)
            186 LOAD_METHOD              7 (reply)
            208 LOAD_CONST               2 ('Provided item id is already being watched')
            210 PRECALL                  1
            214 CALL                     1
            224 GET_AWAITABLE            0
            226 LOAD_CONST               0 (None)
        >>  228 SEND                     3 (to 236)
            230 YIELD_VALUE
            232 RESUME                   3
            234 JUMP_BACKWARD_NO_INTERRUPT     4 (to 228)
        >>  236 RETURN_VALUE

121     >>  238 LOAD_GLOBAL             12 (settings)
            250 LOAD_CONST               1 ('ITEMS')
            252 BINARY_SUBSCR
            262 LOAD_METHOD              8 (append)
            284 LOAD_GLOBAL             11 (NULL + int)
            296 LOAD_FAST                1 (arg1)
            298 PRECALL                  1
            302 CALL                     1
            312 PRECALL                  1
            316 CALL                     1
            326 POP_TOP

122         328 LOAD_GLOBAL             19 (NULL + open)
            340 LOAD_CONST               3 ('settings.json')
            342 LOAD_CONST               4 ('w')
            344 PRECALL                  2
            348 CALL                     2
            358 BEFORE_WITH
            360 STORE_FAST               2 (f)

123         362 LOAD_GLOBAL             21 (NULL + json)
            374 LOAD_ATTR               11 (dump)
            384 LOAD_GLOBAL             12 (settings)
            396 LOAD_FAST                2 (f)
            398 LOAD_CONST               5 (4)
            400 KW_NAMES                 6
            402 PRECALL                  3
            406 CALL                     3
            416 POP_TOP

122         418 LOAD_CONST               0 (None)
            420 LOAD_CONST               0 (None)
            422 LOAD_CONST               0 (None)
            424 PRECALL                  2
            428 CALL                     2
            438 POP_TOP
            440 JUMP_FORWARD            11 (to 464)
        >>  442 PUSH_EXC_INFO
            444 WITH_EXCEPT_START
            446 POP_JUMP_FORWARD_IF_TRUE     4 (to 456)
            448 RERAISE                  2
        >>  450 COPY                     3
            452 POP_EXCEPT
            454 RERAISE                  1
        >>  456 POP_TOP
            458 POP_EXCEPT
            460 POP_TOP
            462 POP_TOP

125     >>  464 LOAD_GLOBAL             21 (NULL + json)
            476 LOAD_ATTR               12 (load)
            486 LOAD_GLOBAL             19 (NULL + open)
            498 LOAD_CONST               3 ('settings.json')
            500 LOAD_CONST               7 ('r')
            502 PRECALL                  2
            506 CALL                     2
            516 PRECALL                  1
            520 CALL                     1
            530 STORE_GLOBAL             6 (settings)

126         532 LOAD_CONST               8 (<code object <listcomp> at 0x000001E65FEAA590, file "main.py", line 126>)
            534 MAKE_FUNCTION            0
            536 LOAD_GLOBAL             12 (settings)
            548 LOAD_CONST               1 ('ITEMS')
            550 BINARY_SUBSCR
            560 GET_ITER
            562 PRECALL                  0
            566 CALL                     0
            576 LOAD_DEREF               3 (self)
            578 LOAD_ATTR               13 (sniper)
            588 STORE_ATTR              14 (watch_items_payload)

127         598 LOAD_CONST               9 (', ')
            600 LOAD_METHOD             15 (join)
            622 LOAD_GLOBAL             33 (NULL + map)
            634 LOAD_GLOBAL              0 (str)
            646 LOAD_GLOBAL             12 (settings)
            658 LOAD_CONST               1 ('ITEMS')
            660 BINARY_SUBSCR
            670 PRECALL                  2
            674 CALL                     2
            684 PRECALL                  1
            688 CALL                     1
            698 LOAD_DEREF               3 (self)
            700 LOAD_ATTR               13 (sniper)
            710 STORE_ATTR              17 (watching_string)

128         720 LOAD_FAST                0 (ctx)
            722 LOAD_METHOD              7 (reply)
            744 LOAD_CONST              10 ('Successfully added ')
            746 LOAD_FAST                1 (arg1)
            748 FORMAT_VALUE             0
            750 BUILD_STRING             2
            752 PRECALL                  1
            756 CALL                     1
            766 GET_AWAITABLE            0
            768 LOAD_CONST               0 (None)
        >>  770 SEND                     3 (to 778)
            772 YIELD_VALUE
            774 RESUME                   3
            776 JUMP_BACKWARD_NO_INTERRUPT     4 (to 770)
        >>  778 RETURN_VALUE

130     >>  780 LOAD_FAST                0 (ctx)
            782 LOAD_METHOD              7 (reply)
            804 LOAD_CONST              11 ('Provided item id is not an int')
            806 PRECALL                  1
            810 CALL                     1
            820 GET_AWAITABLE            0
            822 LOAD_CONST               0 (None)
        >>  824 SEND                     3 (to 832)
            826 YIELD_VALUE
            828 RESUME                   3
            830 JUMP_BACKWARD_NO_INTERRUPT     4 (to 824)
        >>  832 RETURN_VALUE
ExceptionTable:
  360 to 416 -> 442 [1] lasti
  442 to 448 -> 450 [3] lasti
  456 to 456 -> 450 [3] lasti

Disassembly of <code object <listcomp> at 0x000001E65FEAA590, file "main.py", line 126>:
126           0 RESUME                   0
              2 BUILD_LIST               0
              4 LOAD_FAST                0 (.0)
        >>    6 FOR_ITER                 7 (to 22)
              8 STORE_FAST               1 (id)
             10 LOAD_CONST               0 ('Asset')
             12 LOAD_FAST                1 (id)
             14 LOAD_CONST               1 (('itemType', 'id'))
             16 BUILD_CONST_KEY_MAP      2
             18 LIST_APPEND              2
             20 JUMP_BACKWARD            8 (to 6)
        >>   22 RETURN_VALUE

Disassembly of <code object remove at 0x000001E66023F030, file "main.py", line 132>:
              0 COPY_FREE_VARS           1

132           2 RETURN_GENERATOR
              4 POP_TOP
              6 RESUME                   0

136           8 LOAD_GLOBAL              1 (NULL + str)
             20 LOAD_FAST                0 (ctx)
             22 LOAD_ATTR                1 (author)
             32 LOAD_ATTR                2 (id)
             42 PRECALL                  1
             46 CALL                     1
             56 LOAD_DEREF               3 (self)
             58 LOAD_ATTR                3 (owner_id)
             68 COMPARE_OP               3 (!=)
             74 POP_JUMP_FORWARD_IF_FALSE     2 (to 80)

137          76 LOAD_CONST               0 (None)
             78 RETURN_VALUE

139     >>   80 LOAD_FAST                1 (arg1)
             82 EXTENDED_ARG             1
             84 POP_JUMP_FORWARD_IF_FALSE   347 (to 780)
             86 LOAD_FAST                1 (arg1)
             88 LOAD_METHOD              4 (isdigit)
            110 PRECALL                  0
            114 CALL                     0
            124 EXTENDED_ARG             1
            126 POP_JUMP_FORWARD_IF_FALSE   326 (to 780)

140         128 LOAD_GLOBAL             11 (NULL + int)
            140 LOAD_FAST                1 (arg1)
            142 PRECALL                  1
            146 CALL                     1
            156 LOAD_GLOBAL             12 (settings)
            168 LOAD_CONST               1 ('ITEMS')
            170 BINARY_SUBSCR
            180 CONTAINS_OP              1
            182 POP_JUMP_FORWARD_IF_FALSE    27 (to 238)

141         184 LOAD_FAST                0 (ctx)
            186 LOAD_METHOD              7 (reply)
            208 LOAD_CONST               2 ('Provided item id not being watched')
            210 PRECALL                  1
            214 CALL                     1
            224 GET_AWAITABLE            0
            226 LOAD_CONST               0 (None)
        >>  228 SEND                     3 (to 236)
            230 YIELD_VALUE
            232 RESUME                   3
            234 JUMP_BACKWARD_NO_INTERRUPT     4 (to 228)
        >>  236 RETURN_VALUE

143     >>  238 LOAD_GLOBAL             12 (settings)
            250 LOAD_CONST               1 ('ITEMS')
            252 BINARY_SUBSCR
            262 LOAD_METHOD              8 (remove)
            284 LOAD_GLOBAL             11 (NULL + int)
            296 LOAD_FAST                1 (arg1)
            298 PRECALL                  1
            302 CALL                     1
            312 PRECALL                  1
            316 CALL                     1
            326 POP_TOP

144         328 LOAD_GLOBAL             19 (NULL + open)
            340 LOAD_CONST               3 ('settings.json')
            342 LOAD_CONST               4 ('w')
            344 PRECALL                  2
            348 CALL                     2
            358 BEFORE_WITH
            360 STORE_FAST               2 (f)

145         362 LOAD_GLOBAL             21 (NULL + json)
            374 LOAD_ATTR               11 (dump)
            384 LOAD_GLOBAL             12 (settings)
            396 LOAD_FAST                2 (f)
            398 LOAD_CONST               5 (4)
            400 KW_NAMES                 6
            402 PRECALL                  3
            406 CALL                     3
            416 POP_TOP

144         418 LOAD_CONST               0 (None)
            420 LOAD_CONST               0 (None)
            422 LOAD_CONST               0 (None)
            424 PRECALL                  2
            428 CALL                     2
            438 POP_TOP
            440 JUMP_FORWARD            11 (to 464)
        >>  442 PUSH_EXC_INFO
            444 WITH_EXCEPT_START
            446 POP_JUMP_FORWARD_IF_TRUE     4 (to 456)
            448 RERAISE                  2
        >>  450 COPY                     3
            452 POP_EXCEPT
            454 RERAISE                  1
        >>  456 POP_TOP
            458 POP_EXCEPT
            460 POP_TOP
            462 POP_TOP

147     >>  464 LOAD_GLOBAL             21 (NULL + json)
            476 LOAD_ATTR               12 (load)
            486 LOAD_GLOBAL             19 (NULL + open)
            498 LOAD_CONST               3 ('settings.json')
            500 LOAD_CONST               7 ('r')
            502 PRECALL                  2
            506 CALL                     2
            516 PRECALL                  1
            520 CALL                     1
            530 STORE_GLOBAL             6 (settings)

148         532 LOAD_CONST               8 (<code object <listcomp> at 0x000001E65FEAA4C0, file "main.py", line 148>)
            534 MAKE_FUNCTION            0
            536 LOAD_GLOBAL             12 (settings)
            548 LOAD_CONST               1 ('ITEMS')
            550 BINARY_SUBSCR
            560 GET_ITER
            562 PRECALL                  0
            566 CALL                     0
            576 LOAD_DEREF               3 (self)
            578 LOAD_ATTR               13 (sniper)
            588 STORE_ATTR              14 (watch_items_payload)

149         598 LOAD_CONST               9 (', ')
            600 LOAD_METHOD             15 (join)
            622 LOAD_GLOBAL             33 (NULL + map)
            634 LOAD_GLOBAL              0 (str)
            646 LOAD_GLOBAL             12 (settings)
            658 LOAD_CONST               1 ('ITEMS')
            660 BINARY_SUBSCR
            670 PRECALL                  2
            674 CALL                     2
            684 PRECALL                  1
            688 CALL                     1
            698 LOAD_DEREF               3 (self)
            700 LOAD_ATTR               13 (sniper)
            710 STORE_ATTR              17 (watching_string)

150         720 LOAD_FAST                0 (ctx)
            722 LOAD_METHOD              7 (reply)
            744 LOAD_CONST              10 ('Successfully removed ')
            746 LOAD_FAST                1 (arg1)
            748 FORMAT_VALUE             0
            750 BUILD_STRING             2
            752 PRECALL                  1
            756 CALL                     1
            766 GET_AWAITABLE            0
            768 LOAD_CONST               0 (None)
        >>  770 SEND                     3 (to 778)
            772 YIELD_VALUE
            774 RESUME                   3
            776 JUMP_BACKWARD_NO_INTERRUPT     4 (to 770)
        >>  778 RETURN_VALUE

152     >>  780 LOAD_FAST                0 (ctx)
            782 LOAD_METHOD              7 (reply)
            804 LOAD_CONST              11 ('Provided item id is not an int')
            806 PRECALL                  1
            810 CALL                     1
            820 GET_AWAITABLE            0
            822 LOAD_CONST               0 (None)
        >>  824 SEND                     3 (to 832)
            826 YIELD_VALUE
            828 RESUME                   3
            830 JUMP_BACKWARD_NO_INTERRUPT     4 (to 824)
        >>  832 RETURN_VALUE
ExceptionTable:
  360 to 416 -> 442 [1] lasti
  442 to 448 -> 450 [3] lasti
  456 to 456 -> 450 [3] lasti

Disassembly of <code object <listcomp> at 0x000001E65FEAA4C0, file "main.py", line 148>:
148           0 RESUME                   0
              2 BUILD_LIST               0
              4 LOAD_FAST                0 (.0)
        >>    6 FOR_ITER                 7 (to 22)
              8 STORE_FAST               1 (id)
             10 LOAD_CONST               0 ('Asset')
             12 LOAD_FAST                1 (id)
             14 LOAD_CONST               1 (('itemType', 'id'))
             16 BUILD_CONST_KEY_MAP      2
             18 LIST_APPEND              2
             20 JUMP_BACKWARD            8 (to 6)
        >>   22 RETURN_VALUE

Disassembly of <code object remove at 0x000001E6602161C0, file "main.py", line 154>:
              0 COPY_FREE_VARS           1

154           2 RETURN_GENERATOR
              4 POP_TOP
              6 RESUME                   0

158           8 LOAD_GLOBAL              1 (NULL + str)
             20 LOAD_FAST                0 (ctx)
             22 LOAD_ATTR                1 (author)
             32 LOAD_ATTR                2 (id)
             42 PRECALL                  1
             46 CALL                     1
             56 LOAD_DEREF               3 (self)
             58 LOAD_ATTR                3 (owner_id)
             68 COMPARE_OP               3 (!=)
             74 POP_JUMP_FORWARD_IF_FALSE     2 (to 80)

159          76 LOAD_CONST               0 (None)
             78 RETURN_VALUE

161     >>   80 LOAD_FAST                1 (arg1)
             82 EXTENDED_ARG             1
             84 POP_JUMP_FORWARD_IF_FALSE   275 (to 636)
             86 LOAD_FAST                1 (arg1)
             88 LOAD_METHOD              4 (isdigit)
            110 PRECALL                  0
            114 CALL                     0
            124 POP_JUMP_FORWARD_IF_FALSE   255 (to 636)

162         126 LOAD_GLOBAL             11 (NULL + int)
            138 LOAD_FAST                1 (arg1)
            140 PRECALL                  1
            144 CALL                     1
            154 LOAD_GLOBAL             12 (settings)
            166 LOAD_CONST               1 ('BLACKLIST')
            168 BINARY_SUBSCR
            178 CONTAINS_OP              0
            180 POP_JUMP_FORWARD_IF_FALSE    27 (to 236)

163         182 LOAD_FAST                0 (ctx)
            184 LOAD_METHOD              7 (reply)
            206 LOAD_CONST               2 ('Provided item id is already blacklisted')
            208 PRECALL                  1
            212 CALL                     1
            222 GET_AWAITABLE            0
            224 LOAD_CONST               0 (None)
        >>  226 SEND                     3 (to 234)
            228 YIELD_VALUE
            230 RESUME                   3
            232 JUMP_BACKWARD_NO_INTERRUPT     4 (to 226)
        >>  234 RETURN_VALUE

165     >>  236 LOAD_GLOBAL             12 (settings)
            248 LOAD_CONST               1 ('BLACKLIST')
            250 BINARY_SUBSCR
            260 LOAD_METHOD              8 (append)
            282 LOAD_GLOBAL             11 (NULL + int)
            294 LOAD_FAST                1 (arg1)
            296 PRECALL                  1
            300 CALL                     1
            310 PRECALL                  1
            314 CALL                     1
            324 POP_TOP

166         326 LOAD_GLOBAL             19 (NULL + open)
            338 LOAD_CONST               3 ('settings.json')
            340 LOAD_CONST               4 ('w')
            342 PRECALL                  2
            346 CALL                     2
            356 BEFORE_WITH
            358 STORE_FAST               2 (f)

167         360 LOAD_GLOBAL             21 (NULL + json)
            372 LOAD_ATTR               11 (dump)
            382 LOAD_GLOBAL             12 (settings)
            394 LOAD_FAST                2 (f)
            396 LOAD_CONST               5 (4)
            398 KW_NAMES                 6
            400 PRECALL                  3
            404 CALL                     3
            414 POP_TOP

166         416 LOAD_CONST               0 (None)
            418 LOAD_CONST               0 (None)
            420 LOAD_CONST               0 (None)
            422 PRECALL                  2
            426 CALL                     2
            436 POP_TOP
            438 JUMP_FORWARD            11 (to 462)
        >>  440 PUSH_EXC_INFO
            442 WITH_EXCEPT_START
            444 POP_JUMP_FORWARD_IF_TRUE     4 (to 454)
            446 RERAISE                  2
        >>  448 COPY                     3
            450 POP_EXCEPT
            452 RERAISE                  1
        >>  454 POP_TOP
            456 POP_EXCEPT
            458 POP_TOP
            460 POP_TOP

169     >>  462 LOAD_GLOBAL             21 (NULL + json)
            474 LOAD_ATTR               12 (load)
            484 LOAD_GLOBAL             19 (NULL + open)
            496 LOAD_CONST               3 ('settings.json')
            498 LOAD_CONST               7 ('r')
            500 PRECALL                  2
            504 CALL                     2
            514 PRECALL                  1
            518 CALL                     1
            528 STORE_GLOBAL             6 (settings)

170         530 LOAD_GLOBAL             12 (settings)
            542 LOAD_CONST               1 ('BLACKLIST')
            544 BINARY_SUBSCR
            554 LOAD_DEREF               3 (self)
            556 LOAD_ATTR               13 (sniper)
            566 STORE_ATTR              14 (blacklist)

171         576 LOAD_FAST                0 (ctx)
            578 LOAD_METHOD              7 (reply)
            600 LOAD_CONST               8 ('Successfully added ')
            602 LOAD_FAST                1 (arg1)
            604 FORMAT_VALUE             0
            606 BUILD_STRING             2
            608 PRECALL                  1
            612 CALL                     1
            622 GET_AWAITABLE            0
            624 LOAD_CONST               0 (None)
        >>  626 SEND                     3 (to 634)
            628 YIELD_VALUE
            630 RESUME                   3
            632 JUMP_BACKWARD_NO_INTERRUPT     4 (to 626)
        >>  634 RETURN_VALUE

173     >>  636 LOAD_FAST                0 (ctx)
            638 LOAD_METHOD              7 (reply)
            660 LOAD_CONST               9 ('Provided item id is not an int')
            662 PRECALL                  1
            666 CALL                     1
            676 GET_AWAITABLE            0
            678 LOAD_CONST               0 (None)
        >>  680 SEND                     3 (to 688)
            682 YIELD_VALUE
            684 RESUME                   3
            686 JUMP_BACKWARD_NO_INTERRUPT     4 (to 680)
        >>  688 RETURN_VALUE
ExceptionTable:
  358 to 414 -> 440 [1] lasti
  440 to 446 -> 448 [3] lasti
  454 to 454 -> 448 [3] lasti

Disassembly of <code object remove at 0x000001E6603029E0, file "main.py", line 175>:
              0 COPY_FREE_VARS           1

175           2 RETURN_GENERATOR
              4 POP_TOP
              6 RESUME                   0

179           8 LOAD_GLOBAL              1 (NULL + str)
             20 LOAD_FAST                0 (ctx)
             22 LOAD_ATTR                1 (author)
             32 LOAD_ATTR                2 (id)
             42 PRECALL                  1
             46 CALL                     1
             56 LOAD_DEREF               3 (self)
             58 LOAD_ATTR                3 (owner_id)
             68 COMPARE_OP               3 (!=)
             74 POP_JUMP_FORWARD_IF_FALSE     2 (to 80)

180          76 LOAD_CONST               0 (None)
             78 RETURN_VALUE

182     >>   80 LOAD_FAST                1 (arg1)
             82 EXTENDED_ARG             1
             84 POP_JUMP_FORWARD_IF_FALSE   275 (to 636)
             86 LOAD_FAST                1 (arg1)
             88 LOAD_METHOD              4 (isdigit)
            110 PRECALL                  0
            114 CALL                     0
            124 POP_JUMP_FORWARD_IF_FALSE   255 (to 636)

183         126 LOAD_GLOBAL             11 (NULL + int)
            138 LOAD_FAST                1 (arg1)
            140 PRECALL                  1
            144 CALL                     1
            154 LOAD_GLOBAL             12 (settings)
            166 LOAD_CONST               1 ('BLACKLIST')
            168 BINARY_SUBSCR
            178 CONTAINS_OP              1
            180 POP_JUMP_FORWARD_IF_FALSE    27 (to 236)

184         182 LOAD_FAST                0 (ctx)
            184 LOAD_METHOD              7 (reply)
            206 LOAD_CONST               2 ('Provided item id not in blacklist')
            208 PRECALL                  1
            212 CALL                     1
            222 GET_AWAITABLE            0
            224 LOAD_CONST               0 (None)
        >>  226 SEND                     3 (to 234)
            228 YIELD_VALUE
            230 RESUME                   3
            232 JUMP_BACKWARD_NO_INTERRUPT     4 (to 226)
        >>  234 RETURN_VALUE

186     >>  236 LOAD_GLOBAL             12 (settings)
            248 LOAD_CONST               1 ('BLACKLIST')
            250 BINARY_SUBSCR
            260 LOAD_METHOD              8 (remove)
            282 LOAD_GLOBAL             11 (NULL + int)
            294 LOAD_FAST                1 (arg1)
            296 PRECALL                  1
            300 CALL                     1
            310 PRECALL                  1
            314 CALL                     1
            324 POP_TOP

187         326 LOAD_GLOBAL             19 (NULL + open)
            338 LOAD_CONST               3 ('settings.json')
            340 LOAD_CONST               4 ('w')
            342 PRECALL                  2
            346 CALL                     2
            356 BEFORE_WITH
            358 STORE_FAST               2 (f)

188         360 LOAD_GLOBAL             21 (NULL + json)
            372 LOAD_ATTR               11 (dump)
            382 LOAD_GLOBAL             12 (settings)
            394 LOAD_FAST                2 (f)
            396 LOAD_CONST               5 (4)
            398 KW_NAMES                 6
            400 PRECALL                  3
            404 CALL                     3
            414 POP_TOP

187         416 LOAD_CONST               0 (None)
            418 LOAD_CONST               0 (None)
            420 LOAD_CONST               0 (None)
            422 PRECALL                  2
            426 CALL                     2
            436 POP_TOP
            438 JUMP_FORWARD            11 (to 462)
        >>  440 PUSH_EXC_INFO
            442 WITH_EXCEPT_START
            444 POP_JUMP_FORWARD_IF_TRUE     4 (to 454)
            446 RERAISE                  2
        >>  448 COPY                     3
            450 POP_EXCEPT
            452 RERAISE                  1
        >>  454 POP_TOP
            456 POP_EXCEPT
            458 POP_TOP
            460 POP_TOP

190     >>  462 LOAD_GLOBAL             21 (NULL + json)
            474 LOAD_ATTR               12 (load)
            484 LOAD_GLOBAL             19 (NULL + open)
            496 LOAD_CONST               3 ('settings.json')
            498 LOAD_CONST               7 ('r')
            500 PRECALL                  2
            504 CALL                     2
            514 PRECALL                  1
            518 CALL                     1
            528 STORE_GLOBAL             6 (settings)

191         530 LOAD_GLOBAL             12 (settings)
            542 LOAD_CONST               1 ('BLACKLIST')
            544 BINARY_SUBSCR
            554 LOAD_DEREF               3 (self)
            556 LOAD_ATTR               13 (sniper)
            566 STORE_ATTR              14 (blacklist)

192         576 LOAD_FAST                0 (ctx)
            578 LOAD_METHOD              7 (reply)
            600 LOAD_CONST               8 ('Successfully removed ')
            602 LOAD_FAST                1 (arg1)
            604 FORMAT_VALUE             0
            606 BUILD_STRING             2
            608 PRECALL                  1
            612 CALL                     1
            622 GET_AWAITABLE            0
            624 LOAD_CONST               0 (None)
        >>  626 SEND                     3 (to 634)
            628 YIELD_VALUE
            630 RESUME                   3
            632 JUMP_BACKWARD_NO_INTERRUPT     4 (to 626)
        >>  634 RETURN_VALUE

194     >>  636 LOAD_FAST                0 (ctx)
            638 LOAD_METHOD              7 (reply)
            660 LOAD_CONST               9 ('Provided item id is not an int')
            662 PRECALL                  1
            666 CALL                     1
            676 GET_AWAITABLE            0
            678 LOAD_CONST               0 (None)
        >>  680 SEND                     3 (to 688)
            682 YIELD_VALUE
            684 RESUME                   3
            686 JUMP_BACKWARD_NO_INTERRUPT     4 (to 680)
        >>  688 RETURN_VALUE
ExceptionTable:
  358 to 414 -> 440 [1] lasti
  440 to 446 -> 448 [3] lasti
  454 to 454 -> 448 [3] lasti

Disassembly of <code object stats at 0x000001E6602F4700, file "main.py", line 196>:
              0 COPY_FREE_VARS           1

196           2 RETURN_GENERATOR
              4 POP_TOP
              6 RESUME                   0

200           8 LOAD_GLOBAL              1 (NULL + str)
             20 LOAD_FAST                0 (ctx)
             22 LOAD_ATTR                1 (author)
             32 LOAD_ATTR                2 (id)
             42 PRECALL                  1
             46 CALL                     1
             56 LOAD_DEREF               2 (self)
             58 LOAD_ATTR                3 (owner_id)
             68 COMPARE_OP               3 (!=)
             74 POP_JUMP_FORWARD_IF_FALSE     2 (to 80)

201          76 LOAD_CONST               0 (None)
             78 RETURN_VALUE

203     >>   80 LOAD_GLOBAL              9 (NULL + discord)
             92 LOAD_ATTR                5 (Embed)
            102 PRECALL                  0
            106 CALL                     0
            116 STORE_FAST               1 (embed)

204         118 LOAD_CONST               1 ('Mewt Sniper Stats')
            120 LOAD_FAST                1 (embed)
            122 STORE_ATTR               6 (title)

205         132 LOAD_CONST               2 (16234703)
            134 LOAD_FAST                1 (embed)
            136 STORE_ATTR               7 (color)

206         146 LOAD_FAST                1 (embed)
            148 LOAD_METHOD              8 (add_field)
            170 LOAD_CONST               3 ('Bought')
            172 LOAD_CONST               4 ('`')
            174 LOAD_DEREF               2 (self)
            176 LOAD_ATTR                9 (sniper)
            186 LOAD_ATTR               10 (buy_count)
            196 FORMAT_VALUE             0
            198 LOAD_CONST               4 ('`')
            200 BUILD_STRING             3
            202 LOAD_CONST               5 (True)
            204 KW_NAMES                 6
            206 PRECALL                  3
            210 CALL                     3
            220 POP_TOP

207         222 LOAD_FAST                1 (embed)
            224 LOAD_METHOD              8 (add_field)
            246 LOAD_CONST               7 ('Local Thread')
            248 LOAD_CONST               8 ('**Errors**: `')
            250 LOAD_DEREF               2 (self)
            252 LOAD_ATTR                9 (sniper)
            262 LOAD_ATTR               11 (error_count)
            272 FORMAT_VALUE             0
            274 LOAD_CONST               9 ('`\n **Latency**: `')
            276 LOAD_DEREF               2 (self)
            278 LOAD_ATTR                9 (sniper)
            288 LOAD_ATTR               12 (speed_count)
            298 FORMAT_VALUE             0
            300 LOAD_CONST              10 ('`\n **Checks**: `')
            302 LOAD_DEREF               2 (self)
            304 LOAD_ATTR                9 (sniper)
            314 LOAD_ATTR               13 (check_count)
            324 FORMAT_VALUE             0
            326 LOAD_CONST               4 ('`')
            328 BUILD_STRING             7
            330 LOAD_CONST               5 (True)
            332 KW_NAMES                 6
            334 PRECALL                  3
            338 CALL                     3
            348 POP_TOP

208         350 LOAD_GLOBAL             28 (settings)
            362 LOAD_CONST              11 ('MISC')
            364 BINARY_SUBSCR
            374 LOAD_CONST              12 ('PROXIES')
            376 BINARY_SUBSCR
            386 LOAD_CONST              13 ('ENABLED')
            388 BINARY_SUBSCR
            398 POP_JUMP_FORWARD_IF_FALSE    64 (to 528)

209         400 LOAD_FAST                1 (embed)
            402 LOAD_METHOD              8 (add_field)
            424 LOAD_CONST              14 ('Proxy Thread')
            426 LOAD_CONST               8 ('**Errors**: `')
            428 LOAD_DEREF               2 (self)
            430 LOAD_ATTR                9 (sniper)
            440 LOAD_ATTR               15 (proxy_error_count)
            450 FORMAT_VALUE             0
            452 LOAD_CONST               9 ('`\n **Latency**: `')
            454 LOAD_DEREF               2 (self)
            456 LOAD_ATTR                9 (sniper)
            466 LOAD_ATTR               16 (proxy_speed_count)
            476 FORMAT_VALUE             0
            478 LOAD_CONST              10 ('`\n **Checks**: `')
            480 LOAD_DEREF               2 (self)
            482 LOAD_ATTR                9 (sniper)
            492 LOAD_ATTR               17 (proxy_check_count)
            502 FORMAT_VALUE             0
            504 LOAD_CONST               4 ('`')
            506 BUILD_STRING             7
            508 LOAD_CONST               5 (True)
            510 KW_NAMES                 6
            512 PRECALL                  3
            516 CALL                     3
            526 POP_TOP

211     >>  528 LOAD_FAST                0 (ctx)
            530 LOAD_METHOD             18 (reply)
            552 LOAD_FAST                1 (embed)
            554 KW_NAMES                15
            556 PRECALL                  1
            560 CALL                     1
            570 GET_AWAITABLE            0
            572 LOAD_CONST               0 (None)
        >>  574 SEND                     3 (to 582)
            576 YIELD_VALUE
            578 RESUME                   3
            580 JUMP_BACKWARD_NO_INTERRUPT     4 (to 574)
        >>  582 RETURN_VALUE

Disassembly of <code object MewtStyle at 0x000001E660068440, file "main.py", line 216>:
216           0 RESUME                   0
              2 LOAD_NAME                0 (__name__)
              4 STORE_NAME               1 (__module__)
              6 LOAD_CONST               0 ('MewtStyle')
              8 STORE_NAME               2 (__qualname__)

217          10 LOAD_CONST               1 ('\x1b[38;2;247;184;207m')
             12 STORE_NAME               3 (MAIN)
             14 LOAD_CONST               2 (None)
             16 RETURN_VALUE

Disassembly of <code object Client at 0x000001E65FE1BBD0, file "main.py", line 219>:
219           0 RESUME                   0
              2 LOAD_NAME                0 (__name__)
              4 STORE_NAME               1 (__module__)
              6 LOAD_CONST               0 ('Client')
              8 STORE_NAME               2 (__qualname__)

220          10 LOAD_CONST               1 (<code object __init__ at 0x000001E660304CE0, file "main.py", line 220>)
             12 MAKE_FUNCTION            0
             14 STORE_NAME               3 (__init__)

296          16 LOAD_CONST               2 (<code object status_update at 0x000001E660306D00, file "main.py", line 296>)
             18 MAKE_FUNCTION            0
             20 STORE_NAME               4 (status_update)

323          22 LOAD_CONST               3 (<code object initalize_cookie at 0x000001E6602E7960, file "main.py", line 323>)
             24 MAKE_FUNCTION            0
             26 STORE_NAME               5 (initalize_cookie)

335          28 LOAD_CONST               4 (<code object refresh_tokens at 0x000001E660303BA0, file "main.py", line 335>)
             30 MAKE_FUNCTION            0
             32 STORE_NAME               6 (refresh_tokens)

358          34 LOAD_CONST               5 (<code object csrf_updater at 0x000001E65FE19590, file "main.py", line 358>)
             36 MAKE_FUNCTION            0
             38 STORE_NAME               7 (csrf_updater)

365          40 LOAD_CONST               6 ('proxy')
             42 LOAD_NAME                8 (Proxy)
             44 BUILD_TUPLE              2
             46 LOAD_CONST               7 (<code object load_proxy at 0x000001E65FE889F0, file "main.py", line 365>)
             48 MAKE_FUNCTION            4 (annotations)
             50 STORE_NAME               9 (load_proxy)

381          52 LOAD_CONST               8 (<code object load_proxies at 0x000001E660303F30, file "main.py", line 381>)
             54 MAKE_FUNCTION            0
             56 STORE_NAME              10 (load_proxies)

394          58 LOAD_CONST               9 (<code object buy_item at 0x000001E660308950, file "main.py", line 394>)
             60 MAKE_FUNCTION            0
             62 STORE_NAME              11 (buy_item)

463          64 LOAD_CONST              10 (<code object ensure_connection at 0x000001E6603093B0, file "main.py", line 463>)
             66 MAKE_FUNCTION            0
             68 STORE_NAME              12 (ensure_connection)

474          70 LOAD_CONST              11 (<code object auto_search at 0x000001E65FE44AB0, file "main.py", line 474>)
             72 MAKE_FUNCTION            0
             74 STORE_NAME              13 (auto_search)

497          76 LOAD_CONST              12 (<code object post_free_item at 0x000001E660028030, file "main.py", line 497>)
             78 MAKE_FUNCTION            0
             80 STORE_NAME              14 (post_free_item)

505          82 LOAD_CONST              13 (<code object watch_items_proxy at 0x000001E66030AF60, file "main.py", line 505>)
             84 MAKE_FUNCTION            0
             86 STORE_NAME              15 (watch_items_proxy)

561          88 LOAD_CONST              14 (<code object watch_items at 0x000001E66030B670, file "main.py", line 561>)
             90 MAKE_FUNCTION            0
             92 STORE_NAME              16 (watch_items)
             94 LOAD_CONST              15 (None)
             96 RETURN_VALUE

Disassembly of <code object __init__ at 0x000001E660304CE0, file "main.py", line 220>:
220           0 RESUME                   0

221           2 LOAD_GLOBAL              1 (NULL + time)
             14 LOAD_ATTR                0 (time)
             24 PRECALL                  0
             28 CALL                     0
             38 LOAD_FAST                0 (self)
             40 STORE_ATTR               1 (runtime)

222          50 LOAD_CONST               1 ('3.5.3')
             52 LOAD_FAST                0 (self)
             54 STORE_ATTR               2 (version)

223          64 LOAD_GLOBAL              6 (settings)
             76 LOAD_CONST               2 ('MISC')
             78 BINARY_SUBSCR
             88 LOAD_CONST               3 ('WEBHOOK')
             90 BINARY_SUBSCR
            100 LOAD_CONST               4 ('ENABLED')
            102 BINARY_SUBSCR
            112 LOAD_FAST                0 (self)
            114 STORE_ATTR               4 (use_webhook)

224         124 LOAD_GLOBAL              6 (settings)
            136 LOAD_CONST               2 ('MISC')
            138 BINARY_SUBSCR
            148 LOAD_CONST               3 ('WEBHOOK')
            150 BINARY_SUBSCR
            160 LOAD_CONST               5 ('URL')
            162 BINARY_SUBSCR
            172 LOAD_FAST                0 (self)
            174 STORE_ATTR               5 (webhook_uri)

226         184 LOAD_GLOBAL              6 (settings)
            196 LOAD_CONST               6 ('DETAILS_COOKIE')
            198 BINARY_SUBSCR

227         208 LOAD_CONST               7 ('abcabcabc')

225         210 LOAD_CONST               8 (('cookie', 'auth'))
            212 BUILD_CONST_KEY_MAP      2
            214 LOAD_FAST                0 (self)
            216 STORE_ATTR               6 (details_cookie)

230         226 LOAD_GLOBAL              6 (settings)
            238 LOAD_CONST               9 ('MAIN_COOKIE')
            240 BINARY_SUBSCR

231         250 LOAD_CONST               7 ('abcabcabc')

232         252 LOAD_CONST               7 ('abcabcabc')

233         254 LOAD_CONST              10 (0)

229         256 LOAD_CONST              11 (('cookie', 'auth', 'name', 'id'))
            258 BUILD_CONST_KEY_MAP      4
            260 LOAD_FAST                0 (self)
            262 STORE_ATTR               7 (buyer_cookie)

236         272 LOAD_FAST                0 (self)
            274 LOAD_METHOD              8 (initalize_cookie)
            296 PRECALL                  0
            300 CALL                     0
            310 POP_TOP

238         312 LOAD_GLOBAL              6 (settings)
            324 LOAD_CONST               2 ('MISC')
            326 BINARY_SUBSCR
            336 LOAD_CONST              12 ('SCAN_SPEED')
            338 BINARY_SUBSCR
            348 LOAD_FAST                0 (self)
            350 STORE_ATTR               9 (scan_speed)

239         360 LOAD_GLOBAL              6 (settings)
            372 LOAD_CONST               2 ('MISC')
            374 BINARY_SUBSCR
            384 LOAD_CONST              13 ('PROXIES')
            386 BINARY_SUBSCR
            396 LOAD_CONST              12 ('SCAN_SPEED')
            398 BINARY_SUBSCR
            408 LOAD_FAST                0 (self)
            410 STORE_ATTR              10 (proxy_scan_speed)

240         420 LOAD_GLOBAL              6 (settings)
            432 LOAD_CONST               2 ('MISC')
            434 BINARY_SUBSCR
            444 LOAD_CONST              14 ('BUY_ONLY_FREE')
            446 BINARY_SUBSCR
            456 COPY                     1
            458 LOAD_FAST                0 (self)
            460 STORE_ATTR              11 (buy_only_free)
            470 LOAD_FAST                0 (self)
            472 STORE_ATTR              10 (proxy_scan_speed)

241         482 LOAD_CONST              15 (<code object <listcomp> at 0x000001E660068510, file "main.py", line 241>)
            484 MAKE_FUNCTION            0
            486 LOAD_GLOBAL              6 (settings)
            498 LOAD_CONST              16 ('ITEMS')
            500 BINARY_SUBSCR
            510 GET_ITER
            512 PRECALL                  0
            516 CALL                     0
            526 LOAD_FAST                0 (self)
            528 STORE_ATTR              12 (watch_items_payload)

242         538 LOAD_GLOBAL              6 (settings)
            550 LOAD_CONST              17 ('BLACKLIST')
            552 BINARY_SUBSCR
            562 LOAD_FAST                0 (self)
            564 STORE_ATTR              13 (blacklist)

243         574 LOAD_CONST              18 (<code object <dictcomp> at 0x000001E65FE70AB0, file "main.py", line 243>)
            576 MAKE_FUNCTION            0
            578 LOAD_GLOBAL              6 (settings)
            590 LOAD_CONST              16 ('ITEMS')
            592 BINARY_SUBSCR
            602 GET_ITER
            604 PRECALL                  0
            608 CALL                     0
            618 LOAD_FAST                0 (self)
            620 STORE_ATTR              14 (item_pool)

244         630 LOAD_GLOBAL             31 (NULL + KeepAlive)
            642 LOAD_CONST              19 ('apis.roblox.com')
            644 LOAD_CONST              20 (3)
            646 PRECALL                  2
            650 CALL                     2
            660 LOAD_FAST                0 (self)
            662 STORE_ATTR              16 (single_buy)

245         672 LOAD_GLOBAL             31 (NULL + KeepAlive)
            684 LOAD_CONST              19 ('apis.roblox.com')
            686 LOAD_CONST              20 (3)
            688 PRECALL                  2
            692 CALL                     2
            702 LOAD_FAST                0 (self)
            704 STORE_ATTR              17 (auto_search_buy)

246         714 LOAD_GLOBAL             37 (NULL + threading)
            726 LOAD_ATTR               19 (Thread)
            736 LOAD_FAST                0 (self)
            738 LOAD_ATTR               20 (csrf_updater)
            748 KW_NAMES                21
            750 PRECALL                  1
            754 CALL                     1
            764 LOAD_METHOD             21 (start)
            786 PRECALL                  0
            790 CALL                     0
            800 LOAD_FAST                0 (self)
            802 STORE_ATTR              22 (csrf_updater_thread)

247         812 LOAD_GLOBAL             47 (NULL + Webhook)
            824 LOAD_FAST                0 (self)
            826 LOAD_ATTR                5 (webhook_uri)
            836 PRECALL                  1
            840 CALL                     1
            850 LOAD_FAST                0 (self)
            852 STORE_ATTR              24 (webhook)

248         862 LOAD_GLOBAL             51 (NULL + socketio)
            874 LOAD_ATTR               26 (Client)
            884 PRECALL                  0
            888 CALL                     0
            898 LOAD_FAST                0 (self)
            900 STORE_ATTR              27 (auto_socket)

250         910 LOAD_GLOBAL             31 (NULL + KeepAlive)
            922 LOAD_CONST              19 ('apis.roblox.com')
            924 LOAD_CONST              22 (5)
            926 PRECALL                  2
            930 CALL                     2

251         940 LOAD_GLOBAL             31 (NULL + KeepAlive)
            952 LOAD_CONST              19 ('apis.roblox.com')
            954 LOAD_CONST              22 (5)
            956 PRECALL                  2
            960 CALL                     2

252         970 LOAD_GLOBAL             31 (NULL + KeepAlive)
            982 LOAD_CONST              19 ('apis.roblox.com')
            984 LOAD_CONST              22 (5)
            986 PRECALL                  2
            990 CALL                     2

253        1000 LOAD_GLOBAL             31 (NULL + KeepAlive)
           1012 LOAD_CONST              19 ('apis.roblox.com')
           1014 LOAD_CONST              22 (5)
           1016 PRECALL                  2
           1020 CALL                     2

249        1030 BUILD_LIST               4
           1032 LOAD_FAST                0 (self)
           1034 STORE_ATTR              28 (auto_buy_pool)

255        1044 BUILD_LIST               0
           1046 LOAD_FAST                0 (self)
           1048 STORE_ATTR              29 (proxy_pool)

256        1058 BUILD_LIST               0
           1060 LOAD_FAST                0 (self)
           1062 STORE_ATTR              30 (proxy_pool_threads)

257        1072 LOAD_CONST              10 (0)
           1074 LOAD_FAST                0 (self)
           1076 STORE_ATTR              31 (proxy_count)

258        1086 LOAD_CONST              10 (0)
           1088 LOAD_FAST                0 (self)
           1090 STORE_ATTR              32 (check_count)

259        1100 LOAD_CONST              10 (0)
           1102 LOAD_FAST                0 (self)
           1104 STORE_ATTR              33 (error_count)

260        1114 LOAD_CONST              10 (0)
           1116 LOAD_FAST                0 (self)
           1118 STORE_ATTR              34 (speed_count)

261        1128 LOAD_CONST              10 (0)
           1130 LOAD_FAST                0 (self)
           1132 STORE_ATTR              35 (buy_count)

262        1142 LOAD_CONST              10 (0)
           1144 LOAD_FAST                0 (self)
           1146 STORE_ATTR              36 (proxy_check_count)

263        1156 LOAD_CONST              10 (0)
           1158 LOAD_FAST                0 (self)
           1160 STORE_ATTR              37 (proxy_error_count)

264        1170 LOAD_CONST              10 (0)
           1172 LOAD_FAST                0 (self)
           1174 STORE_ATTR              38 (proxy_speed_count)

265        1184 LOAD_CONST              23 (False)
           1186 LOAD_FAST                0 (self)
           1188 STORE_ATTR              39 (ready)

266        1198 BUILD_LIST               0
           1200 LOAD_FAST                0 (self)
           1202 STORE_ATTR              40 (buyingids)

267        1212 LOAD_CONST              24 (', ')
           1214 LOAD_METHOD             41 (join)
           1236 LOAD_GLOBAL             85 (NULL + map)
           1248 LOAD_GLOBAL             86 (str)
           1260 LOAD_GLOBAL              6 (settings)
           1272 LOAD_CONST              16 ('ITEMS')
           1274 BINARY_SUBSCR
           1284 PRECALL                  2
           1288 CALL                     2
           1298 PRECALL                  1
           1302 CALL                     1
           1312 LOAD_FAST                0 (self)
           1314 STORE_ATTR              44 (watching_string)

268        1324 LOAD_CONST              25 ("    \n                                                d8P  \n                                                d888888P\n            88bd8b,d88b  d8888b ?88   d8P  d8P  ?88'  \n            88P'`?8P'?8b d8b_,dP d88  d8P' d8P'  88P   \n            d88  d88  88P 88b     ?8b ,88b ,88'   88b   \n            d88' d88'  88b `?888P' `?888P'888P'    `?8b \n\n                    discord.gg/mewt - v")

276        1326 LOAD_FAST                0 (self)
           1328 LOAD_ATTR                2 (version)

268        1338 FORMAT_VALUE             0
           1340 LOAD_CONST              26 ('                                                    \n        ')
           1342 BUILD_STRING             3
           1344 LOAD_FAST                0 (self)
           1346 STORE_ATTR              45 (title)

278        1356 LOAD_CONST              27 ('None')
           1358 LOAD_FAST                0 (self)
           1360 STORE_ATTR              46 (last_bought)

280        1370 LOAD_FAST                0 (self)
           1372 LOAD_ATTR               39 (ready)
           1382 LOAD_CONST              28 (True)
           1384 COMPARE_OP               3 (!=)
           1390 POP_JUMP_FORWARD_IF_FALSE    31 (to 1454)

281     >> 1392 LOAD_GLOBAL              1 (NULL + time)
           1404 LOAD_ATTR               47 (sleep)
           1414 LOAD_CONST              29 (1)
           1416 PRECALL                  1
           1420 CALL                     1
           1430 POP_TOP

280        1432 LOAD_FAST                0 (self)
           1434 LOAD_ATTR               39 (ready)
           1444 LOAD_CONST              28 (True)
           1446 COMPARE_OP               3 (!=)
           1452 POP_JUMP_BACKWARD_IF_TRUE    31 (to 1392)

283     >> 1454 LOAD_GLOBAL              6 (settings)
           1466 LOAD_CONST               2 ('MISC')
           1468 BINARY_SUBSCR
           1478 LOAD_CONST              13 ('PROXIES')
           1480 BINARY_SUBSCR
           1490 LOAD_CONST               4 ('ENABLED')
           1492 BINARY_SUBSCR
           1502 POP_JUMP_FORWARD_IF_FALSE    99 (to 1702)

284        1504 LOAD_GLOBAL             97 (NULL + print)
           1516 LOAD_CONST              30 ('Loading proxies, this may take a minute')
           1518 PRECALL                  1
           1522 CALL                     1
           1532 POP_TOP

285        1534 LOAD_FAST                0 (self)
           1536 LOAD_METHOD             49 (load_proxies)
           1558 PRECALL                  0
           1562 CALL                     0
           1572 POP_TOP

286        1574 LOAD_GLOBAL             37 (NULL + threading)
           1586 LOAD_ATTR               19 (Thread)
           1596 LOAD_FAST                0 (self)
           1598 LOAD_ATTR               50 (watch_items_proxy)
           1608 KW_NAMES                21
           1610 PRECALL                  1
           1614 CALL                     1
           1624 LOAD_METHOD             21 (start)
           1646 PRECALL                  0
           1650 CALL                     0
           1660 LOAD_FAST                0 (self)
           1662 STORE_ATTR              51 (watch_thread)

287        1672 LOAD_GLOBAL             97 (NULL + print)
           1684 LOAD_CONST              31 ('Successfuly loaded all proxies')
           1686 PRECALL                  1
           1690 CALL                     1
           1700 POP_TOP

289     >> 1702 LOAD_GLOBAL             37 (NULL + threading)
           1714 LOAD_ATTR               19 (Thread)
           1724 LOAD_FAST                0 (self)
           1726 LOAD_ATTR               52 (status_update)
           1736 KW_NAMES                21
           1738 PRECALL                  1
           1742 CALL                     1
           1752 LOAD_METHOD             21 (start)
           1774 PRECALL                  0
           1778 CALL                     0
           1788 LOAD_FAST                0 (self)
           1790 STORE_ATTR              53 (status_update_thread)

290        1800 LOAD_GLOBAL             37 (NULL + threading)
           1812 LOAD_ATTR               19 (Thread)
           1822 LOAD_FAST                0 (self)
           1824 LOAD_ATTR               54 (watch_items)
           1834 KW_NAMES                21
           1836 PRECALL                  1
           1840 CALL                     1
           1850 LOAD_METHOD             21 (start)
           1872 PRECALL                  0
           1876 CALL                     0
           1886 LOAD_FAST                0 (self)
           1888 STORE_ATTR              51 (watch_thread)

291        1898 LOAD_GLOBAL             37 (NULL + threading)
           1910 LOAD_ATTR               19 (Thread)
           1920 LOAD_FAST                0 (self)
           1922 LOAD_ATTR               55 (auto_search)
           1932 KW_NAMES                21
           1934 PRECALL                  1
           1938 CALL                     1
           1948 LOAD_METHOD             21 (start)
           1970 PRECALL                  0
           1974 CALL                     0
           1984 LOAD_FAST                0 (self)
           1986 STORE_ATTR              56 (auto_search_thread)

292        1996 LOAD_GLOBAL              6 (settings)
           2008 LOAD_CONST               2 ('MISC')
           2010 BINARY_SUBSCR
           2020 LOAD_CONST              32 ('DISCORD_BOT')
           2022 BINARY_SUBSCR
           2032 LOAD_CONST               4 ('ENABLED')
           2034 BINARY_SUBSCR
           2044 POP_JUMP_FORWARD_IF_FALSE    95 (to 2236)

293        2046 LOAD_GLOBAL            115 (NULL + Discord)
           2058 LOAD_FAST                0 (self)
           2060 LOAD_GLOBAL              6 (settings)
           2072 LOAD_CONST               2 ('MISC')
           2074 BINARY_SUBSCR
           2084 LOAD_CONST              32 ('DISCORD_BOT')
           2086 BINARY_SUBSCR
           2096 LOAD_CONST              33 ('TOKEN')
           2098 BINARY_SUBSCR
           2108 LOAD_GLOBAL              6 (settings)
           2120 LOAD_CONST               2 ('MISC')
           2122 BINARY_SUBSCR
           2132 LOAD_CONST              32 ('DISCORD_BOT')
           2134 BINARY_SUBSCR
           2144 LOAD_CONST              34 ('OWNER_USER_ID')
           2146 BINARY_SUBSCR
           2156 PRECALL                  3
           2160 CALL                     3
           2170 LOAD_FAST                0 (self)
           2172 STORE_ATTR              58 (discord)

294        2182 LOAD_FAST                0 (self)
           2184 LOAD_ATTR               58 (discord)
           2194 LOAD_METHOD             59 (run)
           2216 PRECALL                  0
           2220 CALL                     0
           2230 POP_TOP
           2232 LOAD_CONST               0 (None)
           2234 RETURN_VALUE

292     >> 2236 LOAD_CONST               0 (None)
           2238 RETURN_VALUE

Disassembly of <code object <listcomp> at 0x000001E660068510, file "main.py", line 241>:
241           0 RESUME                   0
              2 BUILD_LIST               0
              4 LOAD_FAST                0 (.0)
        >>    6 FOR_ITER                 7 (to 22)
              8 STORE_FAST               1 (id)
             10 LOAD_CONST               0 ('Asset')
             12 LOAD_FAST                1 (id)
             14 LOAD_CONST               1 (('itemType', 'id'))
             16 BUILD_CONST_KEY_MAP      2
             18 LIST_APPEND              2
             20 JUMP_BACKWARD            8 (to 6)
        >>   22 RETURN_VALUE

Disassembly of <code object <dictcomp> at 0x000001E65FE70AB0, file "main.py", line 243>:
243           0 RESUME                   0
              2 BUILD_MAP                0
              4 LOAD_FAST                0 (.0)
        >>    6 FOR_ITER                65 (to 138)
              8 STORE_FAST               1 (id)
             10 LOAD_FAST                1 (id)
             12 LOAD_GLOBAL              1 (NULL + KeepAlive)
             24 LOAD_CONST               0 ('apis.roblox.com')
             26 LOAD_CONST               1 (5)
             28 PRECALL                  2
             32 CALL                     2
             42 LOAD_GLOBAL              1 (NULL + KeepAlive)
             54 LOAD_CONST               0 ('apis.roblox.com')
             56 LOAD_CONST               1 (5)
             58 PRECALL                  2
             62 CALL                     2
             72 LOAD_GLOBAL              1 (NULL + KeepAlive)
             84 LOAD_CONST               0 ('apis.roblox.com')
             86 LOAD_CONST               1 (5)
             88 PRECALL                  2
             92 CALL                     2
            102 LOAD_GLOBAL              1 (NULL + KeepAlive)
            114 LOAD_CONST               0 ('apis.roblox.com')
            116 LOAD_CONST               1 (5)
            118 PRECALL                  2
            122 CALL                     2
            132 BUILD_LIST               4
            134 MAP_ADD                  2
            136 JUMP_BACKWARD           66 (to 6)
        >>  138 RETURN_VALUE

Disassembly of <code object status_update at 0x000001E660306D00, file "main.py", line 296>:
296           0 RESUME                   0

297           2 NOP

298     >>    4 LOAD_GLOBAL              1 (NULL + os)
             16 LOAD_ATTR                1 (system)
             26 LOAD_GLOBAL              0 (os)
             38 LOAD_ATTR                2 (name)
             48 LOAD_CONST               2 ('nt')
             50 COMPARE_OP               2 (==)
             56 POP_JUMP_FORWARD_IF_FALSE     2 (to 62)
             58 LOAD_CONST               3 ('cls')
             60 JUMP_FORWARD             1 (to 64)
        >>   62 LOAD_CONST               4 ('clear')
        >>   64 PRECALL                  1
             68 CALL                     1
             78 POP_TOP

299          80 LOAD_GLOBAL              7 (NULL + gradient_print)
             92 LOAD_FAST                0 (self)
             94 LOAD_ATTR                4 (title)
            104 LOAD_CONST               5 (16740003)
            106 LOAD_CONST               6 (16234703)
            108 KW_NAMES                 7
            110 PRECALL                  3
            114 CALL                     3
            124 POP_TOP

301         126 LOAD_GLOBAL             11 (NULL + print)
            138 LOAD_GLOBAL             12 (Fore)
            150 LOAD_ATTR                7 (RESET)
            160 LOAD_GLOBAL             16 (Style)
            172 LOAD_ATTR                9 (RESET_ALL)
            182 BINARY_OP                0 (+)
            186 PRECALL                  1
            190 CALL                     1
            200 POP_TOP

302         202 LOAD_GLOBAL             11 (NULL + print)
            214 LOAD_GLOBAL             16 (Style)
            226 LOAD_ATTR               10 (BRIGHT)
            236 LOAD_CONST               8 ('> Current User: ')
            238 LOAD_GLOBAL             22 (MewtStyle)
            250 LOAD_ATTR               12 (MAIN)
            260 FORMAT_VALUE             0
            262 LOAD_GLOBAL             16 (Style)
            274 LOAD_ATTR               10 (BRIGHT)
            284 FORMAT_VALUE             0
            286 LOAD_FAST                0 (self)
            288 LOAD_ATTR               13 (buyer_cookie)
            298 LOAD_CONST               9 ('name')
            300 BINARY_SUBSCR
            310 FORMAT_VALUE             0
            312 LOAD_GLOBAL             12 (Fore)
            324 LOAD_ATTR               14 (WHITE)
            334 FORMAT_VALUE             0
            336 LOAD_GLOBAL             16 (Style)
            348 LOAD_ATTR               10 (BRIGHT)
            358 FORMAT_VALUE             0
            360 LOAD_CONST              10 (' ')
            362 BUILD_STRING             7
            364 BINARY_OP                0 (+)
            368 PRECALL                  1
            372 CALL                     1
            382 POP_TOP

303         384 LOAD_GLOBAL             11 (NULL + print)
            396 LOAD_GLOBAL             16 (Style)
            408 LOAD_ATTR               10 (BRIGHT)
            418 LOAD_CONST              11 ('> Bought: ')
            420 LOAD_GLOBAL             22 (MewtStyle)
            432 LOAD_ATTR               12 (MAIN)
            442 FORMAT_VALUE             0
            444 LOAD_GLOBAL             16 (Style)
            456 LOAD_ATTR               10 (BRIGHT)
            466 FORMAT_VALUE             0
            468 LOAD_FAST                0 (self)
            470 LOAD_ATTR               15 (buy_count)
            480 FORMAT_VALUE             0
            482 LOAD_GLOBAL             12 (Fore)
            494 LOAD_ATTR               14 (WHITE)
            504 FORMAT_VALUE             0
            506 LOAD_GLOBAL             16 (Style)
            518 LOAD_ATTR               10 (BRIGHT)
            528 FORMAT_VALUE             0
            530 LOAD_CONST              10 (' ')
            532 BUILD_STRING             7
            534 BINARY_OP                0 (+)
            538 PRECALL                  1
            542 CALL                     1
            552 POP_TOP

304         554 LOAD_GLOBAL             11 (NULL + print)
            566 LOAD_GLOBAL             16 (Style)
            578 LOAD_ATTR               10 (BRIGHT)
            588 LOAD_CONST              12 ('> Autosearch: ')
            590 LOAD_GLOBAL             22 (MewtStyle)
            602 LOAD_ATTR               12 (MAIN)
            612 FORMAT_VALUE             0
            614 LOAD_GLOBAL             16 (Style)
            626 LOAD_ATTR               10 (BRIGHT)
            636 FORMAT_VALUE             0
            638 LOAD_FAST                0 (self)
            640 LOAD_ATTR               16 (auto_socket)
            650 LOAD_ATTR               17 (connected)
            660 FORMAT_VALUE             0
            662 LOAD_GLOBAL             12 (Fore)
            674 LOAD_ATTR               14 (WHITE)
            684 FORMAT_VALUE             0
            686 LOAD_GLOBAL             16 (Style)
            698 LOAD_ATTR               10 (BRIGHT)
            708 FORMAT_VALUE             0
            710 LOAD_CONST              10 (' ')
            712 BUILD_STRING             7
            714 BINARY_OP                0 (+)
            718 PRECALL                  1
            722 CALL                     1
            732 POP_TOP

305         734 LOAD_GLOBAL             11 (NULL + print)
            746 LOAD_GLOBAL             16 (Style)
            758 LOAD_ATTR               10 (BRIGHT)
            768 LOAD_CONST              13 ('> Last Bought: ')
            770 LOAD_GLOBAL             22 (MewtStyle)
            782 LOAD_ATTR               12 (MAIN)
            792 FORMAT_VALUE             0
            794 LOAD_GLOBAL             16 (Style)
            806 LOAD_ATTR               10 (BRIGHT)
            816 FORMAT_VALUE             0
            818 LOAD_FAST                0 (self)
            820 LOAD_ATTR               18 (last_bought)
            830 FORMAT_VALUE             0
            832 LOAD_GLOBAL             12 (Fore)
            844 LOAD_ATTR               14 (WHITE)
            854 FORMAT_VALUE             0
            856 LOAD_GLOBAL             16 (Style)
            868 LOAD_ATTR               10 (BRIGHT)
            878 FORMAT_VALUE             0
            880 LOAD_CONST              10 (' ')
            882 BUILD_STRING             7
            884 BINARY_OP                0 (+)
            888 PRECALL                  1
            892 CALL                     1
            902 POP_TOP

306         904 LOAD_GLOBAL             11 (NULL + print)
            916 PRECALL                  0
            920 CALL                     0
            930 POP_TOP

307         932 LOAD_GLOBAL             11 (NULL + print)
            944 LOAD_GLOBAL             16 (Style)
            956 LOAD_ATTR               10 (BRIGHT)
            966 LOAD_CONST              14 ('>> Main')
            968 BINARY_OP                0 (+)
            972 PRECALL                  1
            976 CALL                     1
            986 POP_TOP

308         988 LOAD_GLOBAL             11 (NULL + print)
           1000 LOAD_GLOBAL             16 (Style)
           1012 LOAD_ATTR               10 (BRIGHT)
           1022 LOAD_CONST              15 ('> Errors: ')
           1024 LOAD_GLOBAL             22 (MewtStyle)
           1036 LOAD_ATTR               12 (MAIN)
           1046 FORMAT_VALUE             0
           1048 LOAD_GLOBAL             16 (Style)
           1060 LOAD_ATTR               10 (BRIGHT)
           1070 FORMAT_VALUE             0
           1072 LOAD_FAST                0 (self)
           1074 LOAD_ATTR               19 (error_count)
           1084 FORMAT_VALUE             0
           1086 LOAD_GLOBAL             12 (Fore)
           1098 LOAD_ATTR               14 (WHITE)
           1108 FORMAT_VALUE             0
           1110 LOAD_GLOBAL             16 (Style)
           1122 LOAD_ATTR               10 (BRIGHT)
           1132 FORMAT_VALUE             0
           1134 LOAD_CONST              10 (' ')
           1136 BUILD_STRING             7
           1138 BINARY_OP                0 (+)
           1142 PRECALL                  1
           1146 CALL                     1
           1156 POP_TOP

309        1158 LOAD_GLOBAL             11 (NULL + print)
           1170 LOAD_GLOBAL             16 (Style)
           1182 LOAD_ATTR               10 (BRIGHT)
           1192 LOAD_CONST              16 ('> Latency: ')
           1194 LOAD_GLOBAL             22 (MewtStyle)
           1206 LOAD_ATTR               12 (MAIN)
           1216 FORMAT_VALUE             0
           1218 LOAD_GLOBAL             16 (Style)
           1230 LOAD_ATTR               10 (BRIGHT)
           1240 FORMAT_VALUE             0
           1242 LOAD_FAST                0 (self)
           1244 LOAD_ATTR               20 (speed_count)
           1254 FORMAT_VALUE             0
           1256 LOAD_GLOBAL             12 (Fore)
           1268 LOAD_ATTR               14 (WHITE)
           1278 FORMAT_VALUE             0
           1280 LOAD_GLOBAL             16 (Style)
           1292 LOAD_ATTR               10 (BRIGHT)
           1302 FORMAT_VALUE             0
           1304 LOAD_CONST              10 (' ')
           1306 BUILD_STRING             7
           1308 BINARY_OP                0 (+)
           1312 PRECALL                  1
           1316 CALL                     1
           1326 POP_TOP

310        1328 LOAD_GLOBAL             11 (NULL + print)
           1340 LOAD_GLOBAL             16 (Style)
           1352 LOAD_ATTR               10 (BRIGHT)
           1362 LOAD_CONST              17 ('> Checks: ')
           1364 LOAD_GLOBAL             22 (MewtStyle)
           1376 LOAD_ATTR               12 (MAIN)
           1386 FORMAT_VALUE             0
           1388 LOAD_GLOBAL             16 (Style)
           1400 LOAD_ATTR               10 (BRIGHT)
           1410 FORMAT_VALUE             0
           1412 LOAD_FAST                0 (self)
           1414 LOAD_ATTR               21 (check_count)
           1424 FORMAT_VALUE             0
           1426 LOAD_GLOBAL             12 (Fore)
           1438 LOAD_ATTR               14 (WHITE)
           1448 FORMAT_VALUE             0
           1450 LOAD_GLOBAL             16 (Style)
           1462 LOAD_ATTR               10 (BRIGHT)
           1472 FORMAT_VALUE             0
           1474 LOAD_CONST              10 (' ')
           1476 BUILD_STRING             7
           1478 BINARY_OP                0 (+)
           1482 PRECALL                  1
           1486 CALL                     1
           1496 POP_TOP

311        1498 LOAD_GLOBAL             44 (settings)
           1510 LOAD_CONST              18 ('MISC')
           1512 BINARY_SUBSCR
           1522 LOAD_CONST              19 ('PROXIES')
           1524 BINARY_SUBSCR
           1534 LOAD_CONST              20 ('ENABLED')
           1536 BINARY_SUBSCR
           1546 EXTENDED_ARG             1
           1548 POP_JUMP_FORWARD_IF_FALSE   382 (to 2314)

312        1550 LOAD_GLOBAL             11 (NULL + print)
           1562 PRECALL                  0
           1566 CALL                     0
           1576 POP_TOP

313        1578 LOAD_GLOBAL             11 (NULL + print)
           1590 LOAD_GLOBAL             16 (Style)
           1602 LOAD_ATTR               10 (BRIGHT)
           1612 LOAD_CONST              21 ('>> Proxy')
           1614 BINARY_OP                0 (+)
           1618 PRECALL                  1
           1622 CALL                     1
           1632 POP_TOP

314        1634 LOAD_GLOBAL             11 (NULL + print)
           1646 LOAD_GLOBAL             16 (Style)
           1658 LOAD_ATTR               10 (BRIGHT)
           1668 LOAD_CONST              22 ('> Proxies: ')
           1670 LOAD_GLOBAL             22 (MewtStyle)
           1682 LOAD_ATTR               12 (MAIN)
           1692 FORMAT_VALUE             0
           1694 LOAD_GLOBAL             16 (Style)
           1706 LOAD_ATTR               10 (BRIGHT)
           1716 FORMAT_VALUE             0
           1718 LOAD_FAST                0 (self)
           1720 LOAD_ATTR               23 (proxy_count)
           1730 FORMAT_VALUE             0
           1732 LOAD_GLOBAL             12 (Fore)
           1744 LOAD_ATTR               14 (WHITE)
           1754 FORMAT_VALUE             0
           1756 LOAD_GLOBAL             16 (Style)
           1768 LOAD_ATTR               10 (BRIGHT)
           1778 FORMAT_VALUE             0
           1780 LOAD_CONST              10 (' ')
           1782 BUILD_STRING             7
           1784 BINARY_OP                0 (+)
           1788 PRECALL                  1
           1792 CALL                     1
           1802 POP_TOP

315        1804 LOAD_GLOBAL             11 (NULL + print)
           1816 LOAD_GLOBAL             16 (Style)
           1828 LOAD_ATTR               10 (BRIGHT)
           1838 LOAD_CONST              15 ('> Errors: ')
           1840 LOAD_GLOBAL             22 (MewtStyle)
           1852 LOAD_ATTR               12 (MAIN)
           1862 FORMAT_VALUE             0
           1864 LOAD_GLOBAL             16 (Style)
           1876 LOAD_ATTR               10 (BRIGHT)
           1886 FORMAT_VALUE             0
           1888 LOAD_FAST                0 (self)
           1890 LOAD_ATTR               24 (proxy_error_count)
           1900 FORMAT_VALUE             0
           1902 LOAD_GLOBAL             12 (Fore)
           1914 LOAD_ATTR               14 (WHITE)
           1924 FORMAT_VALUE             0
           1926 LOAD_GLOBAL             16 (Style)
           1938 LOAD_ATTR               10 (BRIGHT)
           1948 FORMAT_VALUE             0
           1950 LOAD_CONST              10 (' ')
           1952 BUILD_STRING             7
           1954 BINARY_OP                0 (+)
           1958 PRECALL                  1
           1962 CALL                     1
           1972 POP_TOP

316        1974 LOAD_GLOBAL             11 (NULL + print)
           1986 LOAD_GLOBAL             16 (Style)
           1998 LOAD_ATTR               10 (BRIGHT)
           2008 LOAD_CONST              16 ('> Latency: ')
           2010 LOAD_GLOBAL             22 (MewtStyle)
           2022 LOAD_ATTR               12 (MAIN)
           2032 FORMAT_VALUE             0
           2034 LOAD_GLOBAL             16 (Style)
           2046 LOAD_ATTR               10 (BRIGHT)
           2056 FORMAT_VALUE             0
           2058 LOAD_FAST                0 (self)
           2060 LOAD_ATTR               25 (proxy_speed_count)
           2070 FORMAT_VALUE             0
           2072 LOAD_GLOBAL             12 (Fore)
           2084 LOAD_ATTR               14 (WHITE)
           2094 FORMAT_VALUE             0
           2096 LOAD_GLOBAL             16 (Style)
           2108 LOAD_ATTR               10 (BRIGHT)
           2118 FORMAT_VALUE             0
           2120 LOAD_CONST              10 (' ')
           2122 BUILD_STRING             7
           2124 BINARY_OP                0 (+)
           2128 PRECALL                  1
           2132 CALL                     1
           2142 POP_TOP

317        2144 LOAD_GLOBAL             11 (NULL + print)
           2156 LOAD_GLOBAL             16 (Style)
           2168 LOAD_ATTR               10 (BRIGHT)
           2178 LOAD_CONST              17 ('> Checks: ')
           2180 LOAD_GLOBAL             22 (MewtStyle)
           2192 LOAD_ATTR               12 (MAIN)
           2202 FORMAT_VALUE             0
           2204 LOAD_GLOBAL             16 (Style)
           2216 LOAD_ATTR               10 (BRIGHT)
           2226 FORMAT_VALUE             0
           2228 LOAD_FAST                0 (self)
           2230 LOAD_ATTR               26 (proxy_check_count)
           2240 FORMAT_VALUE             0
           2242 LOAD_GLOBAL             12 (Fore)
           2254 LOAD_ATTR               14 (WHITE)
           2264 FORMAT_VALUE             0
           2266 LOAD_GLOBAL             16 (Style)
           2278 LOAD_ATTR               10 (BRIGHT)
           2288 FORMAT_VALUE             0
           2290 LOAD_CONST              10 (' ')
           2292 BUILD_STRING             7
           2294 BINARY_OP                0 (+)
           2298 PRECALL                  1
           2302 CALL                     1
           2312 POP_TOP

318     >> 2314 LOAD_GLOBAL             11 (NULL + print)
           2326 PRECALL                  0
           2330 CALL                     0
           2340 POP_TOP

319        2342 LOAD_GLOBAL             11 (NULL + print)
           2354 LOAD_GLOBAL             16 (Style)
           2366 LOAD_ATTR               10 (BRIGHT)
           2376 LOAD_CONST              23 ('> Run Time: ')
           2378 LOAD_GLOBAL             22 (MewtStyle)
           2390 LOAD_ATTR               12 (MAIN)
           2400 FORMAT_VALUE             0
           2402 LOAD_GLOBAL             16 (Style)
           2414 LOAD_ATTR               10 (BRIGHT)
           2424 FORMAT_VALUE             0
           2426 LOAD_GLOBAL             55 (NULL + str)
           2438 LOAD_GLOBAL             57 (NULL + datetime)
           2450 LOAD_ATTR               29 (timedelta)
           2460 LOAD_GLOBAL             61 (NULL + round)
           2472 LOAD_GLOBAL             63 (NULL + time)
           2484 LOAD_ATTR               31 (time)
           2494 PRECALL                  0
           2498 CALL                     0
           2508 LOAD_FAST                0 (self)
           2510 LOAD_ATTR               32 (runtime)
           2520 BINARY_OP               10 (-)
           2524 LOAD_CONST              24 (0)
           2526 PRECALL                  2
           2530 CALL                     2
           2540 KW_NAMES                25
           2542 PRECALL                  1
           2546 CALL                     1
           2556 PRECALL                  1
           2560 CALL                     1
           2570 FORMAT_VALUE             0
           2572 LOAD_GLOBAL             12 (Fore)
           2584 LOAD_ATTR               14 (WHITE)
           2594 FORMAT_VALUE             0
           2596 LOAD_GLOBAL             16 (Style)
           2608 LOAD_ATTR               10 (BRIGHT)
           2618 FORMAT_VALUE             0
           2620 LOAD_CONST              10 (' ')
           2622 BUILD_STRING             7
           2624 BINARY_OP                0 (+)
           2628 PRECALL                  1
           2632 CALL                     1
           2642 POP_TOP

320        2644 LOAD_GLOBAL             11 (NULL + print)
           2656 LOAD_GLOBAL             16 (Style)
           2668 LOAD_ATTR               10 (BRIGHT)
           2678 LOAD_CONST              26 ('> Watching: ')
           2680 LOAD_GLOBAL             22 (MewtStyle)
           2692 LOAD_ATTR               12 (MAIN)
           2702 FORMAT_VALUE             0
           2704 LOAD_GLOBAL             16 (Style)
           2716 LOAD_ATTR               10 (BRIGHT)
           2726 FORMAT_VALUE             0
           2728 LOAD_FAST                0 (self)
           2730 LOAD_ATTR               33 (watching_string)
           2740 FORMAT_VALUE             0
           2742 LOAD_GLOBAL             12 (Fore)
           2754 LOAD_ATTR               14 (WHITE)
           2764 FORMAT_VALUE             0
           2766 LOAD_GLOBAL             16 (Style)
           2778 LOAD_ATTR               10 (BRIGHT)
           2788 FORMAT_VALUE             0
           2790 LOAD_CONST              10 (' ')
           2792 BUILD_STRING             7
           2794 BINARY_OP                0 (+)
           2798 PRECALL                  1
           2802 CALL                     1
           2812 POP_TOP

321        2814 LOAD_GLOBAL             63 (NULL + time)
           2826 LOAD_ATTR               34 (sleep)
           2836 LOAD_CONST              27 (1)
           2838 PRECALL                  1
           2842 CALL                     1
           2852 POP_TOP

297        2854 EXTENDED_ARG             5
           2856 JUMP_BACKWARD         1427 (to 4)

Disassembly of <code object initalize_cookie at 0x000001E6602E7960, file "main.py", line 323>:
323           0 RESUME                   0

324           2 LOAD_GLOBAL              1 (NULL + requests)
             14 LOAD_ATTR                1 (session)
             24 PRECALL                  0
             28 CALL                     0
             38 BEFORE_WITH
             40 STORE_FAST               1 (session)

325          42 LOAD_FAST                0 (self)
             44 LOAD_ATTR                2 (buyer_cookie)
             54 LOAD_CONST               1 ('cookie')
             56 BINARY_SUBSCR
             66 LOAD_FAST                1 (session)
             68 LOAD_ATTR                3 (cookies)
             78 LOAD_CONST               2 ('.ROBLOSECURITY')
             80 STORE_SUBSCR

326          84 LOAD_FAST                1 (session)
             86 LOAD_METHOD              4 (get)
            108 LOAD_CONST               3 ('https://users.roblox.com/v1/users/authenticated')
            110 PRECALL                  1
            114 CALL                     1
            124 STORE_FAST               2 (conn)

327         126 LOAD_FAST                2 (conn)
            128 LOAD_ATTR                5 (status_code)
            138 LOAD_CONST               4 (200)
            140 COMPARE_OP               2 (==)
            146 POP_JUMP_FORWARD_IF_FALSE    53 (to 254)

328         148 LOAD_FAST                2 (conn)
            150 LOAD_METHOD              6 (json)
            172 PRECALL                  0
            176 CALL                     0
            186 STORE_FAST               3 (data)

329         188 LOAD_FAST                3 (data)
            190 LOAD_CONST               5 ('id')
            192 BINARY_SUBSCR
            202 LOAD_FAST                0 (self)
            204 LOAD_ATTR                2 (buyer_cookie)
            214 LOAD_CONST               5 ('id')
            216 STORE_SUBSCR

330         220 LOAD_FAST                3 (data)
            222 LOAD_CONST               6 ('name')
            224 BINARY_SUBSCR
            234 LOAD_FAST                0 (self)
            236 LOAD_ATTR                2 (buyer_cookie)
            246 LOAD_CONST               6 ('name')
            248 STORE_SUBSCR
            252 JUMP_FORWARD            22 (to 298)

332     >>  254 LOAD_GLOBAL             15 (NULL + print)
            266 LOAD_CONST               7 ('Invalid main cookie or please wait a minute and trying again')
            268 PRECALL                  1
            272 CALL                     1
            282 POP_TOP

333         284 LOAD_GLOBAL             16 (SystemExit)
            296 RAISE_VARARGS            1

330     >>  298 NOP

324         300 LOAD_CONST               0 (None)
            302 LOAD_CONST               0 (None)
            304 LOAD_CONST               0 (None)
            306 PRECALL                  2
            310 CALL                     2
            320 POP_TOP
            322 LOAD_CONST               0 (None)
            324 RETURN_VALUE
        >>  326 PUSH_EXC_INFO
            328 WITH_EXCEPT_START
            330 POP_JUMP_FORWARD_IF_TRUE     4 (to 340)
            332 RERAISE                  2
        >>  334 COPY                     3
            336 POP_EXCEPT
            338 RERAISE                  1
        >>  340 POP_TOP
            342 POP_EXCEPT
            344 POP_TOP
            346 POP_TOP
            348 LOAD_CONST               0 (None)
            350 RETURN_VALUE
ExceptionTable:
  40 to 296 -> 326 [1] lasti
  326 to 332 -> 334 [3] lasti
  340 to 340 -> 334 [3] lasti

Disassembly of <code object refresh_tokens at 0x000001E660303BA0, file "main.py", line 335>:
335           0 RESUME                   0

336           2 LOAD_GLOBAL              1 (NULL + requests)
             14 LOAD_ATTR                1 (session)
             24 PRECALL                  0
             28 CALL                     0
             38 BEFORE_WITH
             40 STORE_FAST               1 (session)

337          42 LOAD_FAST                0 (self)
             44 LOAD_ATTR                2 (buyer_cookie)
             54 LOAD_CONST               1 ('cookie')
             56 BINARY_SUBSCR
             66 LOAD_FAST                1 (session)
             68 LOAD_ATTR                3 (cookies)
             78 LOAD_CONST               2 ('.ROBLOSECURITY')
             80 STORE_SUBSCR

338          84 LOAD_FAST                1 (session)
             86 LOAD_METHOD              4 (post)
            108 LOAD_CONST               3 ('https://friends.roblox.com/v1/users/1/request-friendship')
            110 PRECALL                  1
            114 CALL                     1
            124 STORE_FAST               2 (conn)

339         126 LOAD_FAST                2 (conn)
            128 LOAD_ATTR                5 (headers)
            138 LOAD_METHOD              6 (get)
            160 LOAD_CONST               4 ('x-csrf-token')
            162 PRECALL                  1
            166 CALL                     1
            176 POP_JUMP_FORWARD_IF_FALSE    22 (to 222)

340         178 LOAD_FAST                2 (conn)
            180 LOAD_ATTR                5 (headers)
            190 LOAD_CONST               4 ('x-csrf-token')
            192 BINARY_SUBSCR
            202 LOAD_FAST                0 (self)
            204 LOAD_ATTR                2 (buyer_cookie)
            214 LOAD_CONST               5 ('auth')
            216 STORE_SUBSCR
            220 JUMP_FORWARD            42 (to 306)

342     >>  222 LOAD_GLOBAL             15 (NULL + print)
            234 LOAD_CONST               6 ('Invalid main cookie, unable to fetch x-csrf-token')
            236 PRECALL                  1
            240 CALL                     1
            250 POP_TOP

343         252 LOAD_GLOBAL             17 (NULL + time)
            264 LOAD_ATTR                9 (sleep)
            274 LOAD_CONST               7 (1)
            276 PRECALL                  1
            280 CALL                     1
            290 POP_TOP

344         292 LOAD_GLOBAL             20 (SystemExit)
            304 RAISE_VARARGS            1

340     >>  306 NOP

336         308 LOAD_CONST               0 (None)
            310 LOAD_CONST               0 (None)
            312 LOAD_CONST               0 (None)
            314 PRECALL                  2
            318 CALL                     2
            328 POP_TOP
            330 JUMP_FORWARD            11 (to 354)
        >>  332 PUSH_EXC_INFO
            334 WITH_EXCEPT_START
            336 POP_JUMP_FORWARD_IF_TRUE     4 (to 346)
            338 RERAISE                  2
        >>  340 COPY                     3
            342 POP_EXCEPT
            344 RERAISE                  1
        >>  346 POP_TOP
            348 POP_EXCEPT
            350 POP_TOP
            352 POP_TOP

347     >>  354 LOAD_GLOBAL              1 (NULL + requests)
            366 LOAD_ATTR                1 (session)
            376 PRECALL                  0
            380 CALL                     0
            390 BEFORE_WITH
            392 STORE_FAST               1 (session)

348         394 LOAD_FAST                0 (self)
            396 LOAD_ATTR               11 (details_cookie)
            406 LOAD_CONST               1 ('cookie')
            408 BINARY_SUBSCR
            418 LOAD_FAST                1 (session)
            420 LOAD_ATTR                3 (cookies)
            430 LOAD_CONST               2 ('.ROBLOSECURITY')
            432 STORE_SUBSCR

349         436 LOAD_FAST                1 (session)
            438 LOAD_METHOD              4 (post)
            460 LOAD_CONST               3 ('https://friends.roblox.com/v1/users/1/request-friendship')
            462 PRECALL                  1
            466 CALL                     1
            476 STORE_FAST               2 (conn)

350         478 LOAD_FAST                2 (conn)
            480 LOAD_ATTR                5 (headers)
            490 LOAD_METHOD              6 (get)
            512 LOAD_CONST               4 ('x-csrf-token')
            514 PRECALL                  1
            518 CALL                     1
            528 POP_JUMP_FORWARD_IF_FALSE    22 (to 574)

351         530 LOAD_FAST                2 (conn)
            532 LOAD_ATTR                5 (headers)
            542 LOAD_CONST               4 ('x-csrf-token')
            544 BINARY_SUBSCR
            554 LOAD_FAST                0 (self)
            556 LOAD_ATTR               11 (details_cookie)
            566 LOAD_CONST               5 ('auth')
            568 STORE_SUBSCR
            572 JUMP_FORWARD            42 (to 658)

353     >>  574 LOAD_GLOBAL             15 (NULL + print)
            586 LOAD_CONST               8 ('Invalid alt cookie, unable to fetch x-csrf-token')
            588 PRECALL                  1
            592 CALL                     1
            602 POP_TOP

354         604 LOAD_GLOBAL             17 (NULL + time)
            616 LOAD_ATTR                9 (sleep)
            626 LOAD_CONST               7 (1)
            628 PRECALL                  1
            632 CALL                     1
            642 POP_TOP

355         644 LOAD_GLOBAL             20 (SystemExit)
            656 RAISE_VARARGS            1

351     >>  658 NOP

347         660 LOAD_CONST               0 (None)
            662 LOAD_CONST               0 (None)
            664 LOAD_CONST               0 (None)
            666 PRECALL                  2
            670 CALL                     2
            680 POP_TOP
            682 LOAD_CONST               0 (None)
            684 RETURN_VALUE
        >>  686 PUSH_EXC_INFO
            688 WITH_EXCEPT_START
            690 POP_JUMP_FORWARD_IF_TRUE     4 (to 700)
            692 RERAISE                  2
        >>  694 COPY                     3
            696 POP_EXCEPT
            698 RERAISE                  1
        >>  700 POP_TOP
            702 POP_EXCEPT
            704 POP_TOP
            706 POP_TOP
            708 LOAD_CONST               0 (None)
            710 RETURN_VALUE
ExceptionTable:
  40 to 304 -> 332 [1] lasti
  332 to 338 -> 340 [3] lasti
  346 to 346 -> 340 [3] lasti
  392 to 656 -> 686 [1] lasti
  686 to 692 -> 694 [3] lasti
  700 to 700 -> 694 [3] lasti

Disassembly of <code object csrf_updater at 0x000001E65FE19590, file "main.py", line 358>:
358           0 RESUME                   0

359           2 NOP

360     >>    4 LOAD_FAST                0 (self)
              6 LOAD_METHOD              0 (refresh_tokens)
             28 PRECALL                  0
             32 CALL                     0
             42 POP_TOP

362          44 LOAD_CONST               1 (True)
             46 LOAD_FAST                0 (self)
             48 STORE_ATTR               1 (ready)

363          58 LOAD_GLOBAL              5 (NULL + time)
             70 LOAD_ATTR                3 (sleep)
             80 LOAD_CONST               2 (200)
             82 PRECALL                  1
             86 CALL                     1
             96 POP_TOP

359          98 JUMP_BACKWARD           48 (to 4)

Disassembly of <code object load_proxy at 0x000001E65FE889F0, file "main.py", line 365>:
365           0 RESUME                   0

366           2 LOAD_GLOBAL              1 (NULL + requests)
             14 LOAD_ATTR                1 (post)

367          24 LOAD_CONST               1 ('https://catalog.roblox.com/v1/catalog/items/details')

369          26 LOAD_FAST                1 (proxy)
             28 LOAD_ATTR                2 (url)

370          38 LOAD_FAST                1 (proxy)
             40 LOAD_ATTR                2 (url)

368          50 LOAD_CONST               2 (('http', 'https'))
             52 BUILD_CONST_KEY_MAP      2

366          54 KW_NAMES                 3
             56 PRECALL                  2
             60 CALL                     2
             70 STORE_FAST               2 (response)

374          72 LOAD_FAST                2 (response)
             74 LOAD_ATTR                3 (status_code)
             84 LOAD_CONST               4 (403)
             86 COMPARE_OP               2 (==)
             92 POP_JUMP_FORWARD_IF_FALSE    22 (to 138)

375          94 LOAD_FAST                2 (response)
             96 LOAD_ATTR                4 (headers)
            106 STORE_FAST               3 (headers)

376         108 LOAD_FAST                3 (headers)
            110 LOAD_CONST               5 ('x-csrf-token')
            112 BINARY_SUBSCR
            122 LOAD_FAST                1 (proxy)
            124 STORE_ATTR               5 (auth)
            134 LOAD_CONST               0 (None)
            136 RETURN_VALUE

378     >>  138 LOAD_GLOBAL             13 (NULL + time)
            150 LOAD_ATTR                7 (sleep)
            160 LOAD_CONST               6 (10)
            162 PRECALL                  1
            166 CALL                     1
            176 POP_TOP

379         178 LOAD_FAST                0 (self)
            180 LOAD_METHOD              8 (load_proxy)
            202 LOAD_FAST                1 (proxy)
            204 PRECALL                  1
            208 CALL                     1
            218 POP_TOP
            220 LOAD_CONST               0 (None)
            222 RETURN_VALUE

Disassembly of <code object load_proxies at 0x000001E660303F30, file "main.py", line 381>:
381           0 RESUME                   0

382           2 LOAD_GLOBAL              1 (NULL + open)
             14 LOAD_CONST               1 ('proxies.txt')
             16 LOAD_CONST               2 ('r')
             18 PRECALL                  2
             22 CALL                     2
             32 LOAD_METHOD              1 (read)
             54 PRECALL                  0
             58 CALL                     0
             68 LOAD_METHOD              2 (splitlines)
             90 PRECALL                  0
             94 CALL                     0
            104 STORE_FAST               1 (proxies_txt)

383         106 LOAD_GLOBAL              7 (NULL + len)
            118 LOAD_FAST                1 (proxies_txt)
            120 PRECALL                  1
            124 CALL                     1
            134 LOAD_FAST                0 (self)
            136 STORE_ATTR               4 (proxy_count)

384         146 LOAD_GLOBAL             11 (NULL + enumerate)
            158 LOAD_FAST                1 (proxies_txt)
            160 PRECALL                  1
            164 CALL                     1
            174 GET_ITER
        >>  176 FOR_ITER               120 (to 418)
            178 UNPACK_SEQUENCE          2
            182 STORE_FAST               2 (_)
            184 STORE_FAST               3 (raw_proxy)

385         186 LOAD_GLOBAL             13 (NULL + Proxy)
            198 LOAD_FAST                3 (raw_proxy)
            200 PRECALL                  1
            204 CALL                     1
            214 STORE_FAST               4 (proxy)

386         216 LOAD_FAST                0 (self)
            218 LOAD_ATTR                7 (proxy_pool)
            228 LOAD_METHOD              8 (append)
            250 LOAD_FAST                4 (proxy)
            252 PRECALL                  1
            256 CALL                     1
            266 POP_TOP

387         268 LOAD_GLOBAL             19 (NULL + threading)
            280 LOAD_ATTR               10 (Thread)
            290 LOAD_FAST                0 (self)
            292 LOAD_ATTR               11 (load_proxy)
            302 LOAD_FAST                4 (proxy)
            304 BUILD_TUPLE              1
            306 KW_NAMES                 3
            308 PRECALL                  2
            312 CALL                     2
            322 STORE_FAST               5 (thread)

388         324 LOAD_FAST                5 (thread)
            326 LOAD_METHOD             12 (start)
            348 PRECALL                  0
            352 CALL                     0
            362 POP_TOP

389         364 LOAD_FAST                0 (self)
            366 LOAD_ATTR               13 (proxy_pool_threads)
            376 LOAD_METHOD              8 (append)
            398 LOAD_FAST                5 (thread)
            400 PRECALL                  1
            404 CALL                     1
            414 POP_TOP
            416 JUMP_BACKWARD          121 (to 176)

391     >>  418 LOAD_FAST                0 (self)
            420 LOAD_ATTR               13 (proxy_pool_threads)
            430 GET_ITER
        >>  432 FOR_ITER                22 (to 478)
            434 STORE_FAST               5 (thread)

392         436 LOAD_FAST                5 (thread)
            438 LOAD_METHOD             14 (join)
            460 PRECALL                  0
            464 CALL                     0
            474 POP_TOP
            476 JUMP_BACKWARD           23 (to 432)

391     >>  478 LOAD_CONST               0 (None)
            480 RETURN_VALUE

Disassembly of <code object buy_item at 0x000001E660308950, file "main.py", line 394>:
394           0 RESUME                   0

395           2 LOAD_GLOBAL              1 (NULL + json)
             14 LOAD_ATTR                1 (dumps)

397          24 LOAD_GLOBAL              5 (NULL + str)
             36 LOAD_FAST                1 (details)
             38 LOAD_CONST               1 ('collectibleItemId')
             40 BINARY_SUBSCR
             50 PRECALL                  1
             54 CALL                     1

398          64 LOAD_CONST               2 (1)

399          66 LOAD_FAST                3 (d_data)
             68 LOAD_CONST               3 ('price')
             70 BINARY_SUBSCR

400          80 LOAD_FAST                0 (self)
             82 LOAD_ATTR                3 (buyer_cookie)
             92 LOAD_CONST               4 ('id')
             94 BINARY_SUBSCR

401         104 LOAD_CONST               5 ('User')

402         106 LOAD_FAST                3 (d_data)
            108 LOAD_CONST               6 ('creatorId')
            110 BINARY_SUBSCR

403         120 LOAD_CONST               5 ('User')

404         122 LOAD_GLOBAL              5 (NULL + str)
            134 LOAD_GLOBAL              9 (NULL + uuid)
            146 LOAD_ATTR                5 (uuid4)
            156 PRECALL                  0
            160 CALL                     0
            170 PRECALL                  1
            174 CALL                     1

405         184 LOAD_FAST                3 (d_data)
            186 LOAD_CONST               7 ('collectibleProductId')
            188 BINARY_SUBSCR

396         198 LOAD_CONST               8 (('collectibleItemId', 'expectedCurrency', 'expectedPrice', 'expectedPurchaserId', 'expectedPurchaserType', 'expectedSellerId', 'expectedSellerType', 'idempotencyKey', 'collectibleProductId'))
            200 BUILD_CONST_KEY_MAP      9

395         202 PRECALL                  1
            206 CALL                     1
            216 STORE_FAST               5 (payload)

408         218 NOP

409         220 LOAD_FAST                2 (conn)
            222 LOAD_METHOD              6 (get)
            244 PRECALL                  0
            248 CALL                     0
            258 STORE_FAST               2 (conn)

410         260 LOAD_FAST                2 (conn)
            262 LOAD_METHOD              7 (request)

411         284 LOAD_CONST               9 ('POST')

412         286 LOAD_CONST              10 ('/marketplace-sales/v1/item/')
            288 LOAD_FAST                1 (details)
            290 LOAD_CONST               1 ('collectibleItemId')
            292 BINARY_SUBSCR
            302 FORMAT_VALUE             0
            304 LOAD_CONST              11 ('/purchase-item')
            306 BUILD_STRING             3

413         308 LOAD_FAST                5 (payload)

414         310 LOAD_CONST              12 ('application/json')
            312 LOAD_CONST              13 ('.ROBLOSECURITY=%s')
            314 LOAD_FAST                0 (self)
            316 LOAD_ATTR                3 (buyer_cookie)
            326 LOAD_CONST              14 ('cookie')
            328 BINARY_SUBSCR
            338 BINARY_OP                6 (%)
            342 LOAD_FAST                0 (self)
            344 LOAD_ATTR                3 (buyer_cookie)
            354 LOAD_CONST              15 ('auth')
            356 BINARY_SUBSCR
            366 LOAD_CONST              16 (('Content-Type', 'Cookie', 'x-csrf-token'))
            368 BUILD_CONST_KEY_MAP      3

410         370 KW_NAMES                17
            372 PRECALL                  4
            376 CALL                     4
            386 POP_TOP

416         388 NOP

417         390 LOAD_FAST                2 (conn)
            392 LOAD_METHOD              8 (getresponse)
            414 PRECALL                  0
            418 CALL                     0
            428 STORE_FAST               6 (resp)
            430 JUMP_FORWARD           143 (to 718)
        >>  432 PUSH_EXC_INFO

418         434 LOAD_GLOBAL             18 (http)
            446 LOAD_ATTR               10 (client)
            456 LOAD_ATTR               11 (ResponseNotReady)
            466 CHECK_EXC_MATCH
            468 POP_JUMP_FORWARD_IF_FALSE   120 (to 710)
            470 POP_TOP

419         472 LOAD_FAST                2 (conn)
            474 LOAD_METHOD             12 (close)
            496 PRECALL                  0
            500 CALL                     0
            510 POP_TOP

420         512 LOAD_FAST                1 (details)
            514 LOAD_CONST               4 ('id')
            516 BINARY_SUBSCR
            526 LOAD_FAST                0 (self)
            528 LOAD_ATTR               13 (buyingids)
            538 CONTAINS_OP              0
            540 POP_JUMP_FORWARD_IF_FALSE    32 (to 606)

421         542 LOAD_FAST                0 (self)
            544 LOAD_ATTR               13 (buyingids)
            554 LOAD_METHOD             14 (remove)
            576 LOAD_FAST                1 (details)
            578 LOAD_CONST               4 ('id')
            580 BINARY_SUBSCR
            590 PRECALL                  1
            594 CALL                     1
            604 POP_TOP

422     >>  606 POP_EXCEPT

459         608 LOAD_FAST                1 (details)
            610 LOAD_CONST               4 ('id')
            612 BINARY_SUBSCR
            622 LOAD_FAST                0 (self)
            624 LOAD_ATTR               13 (buyingids)
            634 CONTAINS_OP              0
            636 POP_JUMP_FORWARD_IF_FALSE    34 (to 706)

460         638 LOAD_FAST                0 (self)
            640 LOAD_ATTR               13 (buyingids)
            650 LOAD_METHOD             14 (remove)
            672 LOAD_FAST                1 (details)
            674 LOAD_CONST               4 ('id')
            676 BINARY_SUBSCR
            686 PRECALL                  1
            690 CALL                     1
            700 POP_TOP
            702 LOAD_CONST               0 (None)
            704 RETURN_VALUE

459     >>  706 LOAD_CONST               0 (None)
            708 RETURN_VALUE

418     >>  710 RERAISE                  0
        >>  712 COPY                     3
            714 POP_EXCEPT
            716 RERAISE                  1

424     >>  718 LOAD_FAST                6 (resp)
            720 LOAD_ATTR               15 (status)
            730 LOAD_CONST              18 (429)
            732 COMPARE_OP               2 (==)
            738 POP_JUMP_FORWARD_IF_FALSE   170 (to 1080)

425         740 LOAD_GLOBAL             33 (NULL + print)
            752 LOAD_CONST              19 ('Buying - Ratelimited')
            754 PRECALL                  1
            758 CALL                     1
            768 POP_TOP

426         770 LOAD_FAST                0 (self)
            772 COPY                     1
            774 LOAD_ATTR               17 (error_count)
            784 LOAD_CONST               2 (1)
            786 BINARY_OP               13 (+=)
            790 SWAP                     2
            792 STORE_ATTR              17 (error_count)

427         802 LOAD_GLOBAL             37 (NULL + time)
            814 LOAD_ATTR               19 (sleep)
            824 LOAD_CONST              20 (0.5)
            826 PRECALL                  1
            830 CALL                     1
            840 POP_TOP

428         842 LOAD_FAST                2 (conn)
            844 LOAD_METHOD             12 (close)
            866 PRECALL                  0
            870 CALL                     0
            880 POP_TOP

429         882 LOAD_FAST                1 (details)
            884 LOAD_CONST               4 ('id')
            886 BINARY_SUBSCR
            896 LOAD_FAST                0 (self)
            898 LOAD_ATTR               13 (buyingids)
            908 CONTAINS_OP              0
            910 POP_JUMP_FORWARD_IF_FALSE    32 (to 976)

430         912 LOAD_FAST                0 (self)
            914 LOAD_ATTR               13 (buyingids)
            924 LOAD_METHOD             14 (remove)
            946 LOAD_FAST                1 (details)
            948 LOAD_CONST               4 ('id')
            950 BINARY_SUBSCR
            960 PRECALL                  1
            964 CALL                     1
            974 POP_TOP

431     >>  976 NOP

459         978 LOAD_FAST                1 (details)
            980 LOAD_CONST               4 ('id')
            982 BINARY_SUBSCR
            992 LOAD_FAST                0 (self)
            994 LOAD_ATTR               13 (buyingids)
           1004 CONTAINS_OP              0
           1006 POP_JUMP_FORWARD_IF_FALSE    34 (to 1076)

460        1008 LOAD_FAST                0 (self)
           1010 LOAD_ATTR               13 (buyingids)
           1020 LOAD_METHOD             14 (remove)
           1042 LOAD_FAST                1 (details)
           1044 LOAD_CONST               4 ('id')
           1046 BINARY_SUBSCR
           1056 PRECALL                  1
           1060 CALL                     1
           1070 POP_TOP
           1072 LOAD_CONST               0 (None)
           1074 RETURN_VALUE

459     >> 1076 LOAD_CONST               0 (None)
           1078 RETURN_VALUE

432     >> 1080 NOP

433        1082 LOAD_GLOBAL              1 (NULL + json)
           1094 LOAD_ATTR               20 (loads)
           1104 LOAD_FAST                6 (resp)
           1106 LOAD_METHOD             21 (read)
           1128 PRECALL                  0
           1132 CALL                     0
           1142 PRECALL                  1
           1146 CALL                     1
           1156 STORE_FAST               7 (data)
           1158 JUMP_FORWARD           124 (to 1408)
        >> 1160 PUSH_EXC_INFO

434        1162 POP_TOP

435        1164 LOAD_FAST                2 (conn)
           1166 LOAD_METHOD             12 (close)
           1188 PRECALL                  0
           1192 CALL                     0
           1202 POP_TOP

436        1204 LOAD_FAST                1 (details)
           1206 LOAD_CONST               4 ('id')
           1208 BINARY_SUBSCR
           1218 LOAD_FAST                0 (self)
           1220 LOAD_ATTR               13 (buyingids)
           1230 CONTAINS_OP              0
           1232 POP_JUMP_FORWARD_IF_FALSE    32 (to 1298)

437        1234 LOAD_FAST                0 (self)
           1236 LOAD_ATTR               13 (buyingids)
           1246 LOAD_METHOD             14 (remove)
           1268 LOAD_FAST                1 (details)
           1270 LOAD_CONST               4 ('id')
           1272 BINARY_SUBSCR
           1282 PRECALL                  1
           1286 CALL                     1
           1296 POP_TOP

438     >> 1298 POP_EXCEPT

459        1300 LOAD_FAST                1 (details)
           1302 LOAD_CONST               4 ('id')
           1304 BINARY_SUBSCR
           1314 LOAD_FAST                0 (self)
           1316 LOAD_ATTR               13 (buyingids)
           1326 CONTAINS_OP              0
           1328 POP_JUMP_FORWARD_IF_FALSE    34 (to 1398)

460        1330 LOAD_FAST                0 (self)
           1332 LOAD_ATTR               13 (buyingids)
           1342 LOAD_METHOD             14 (remove)
           1364 LOAD_FAST                1 (details)
           1366 LOAD_CONST               4 ('id')
           1368 BINARY_SUBSCR
           1378 PRECALL                  1
           1382 CALL                     1
           1392 POP_TOP
           1394 LOAD_CONST               0 (None)
           1396 RETURN_VALUE

459     >> 1398 LOAD_CONST               0 (None)
           1400 RETURN_VALUE
        >> 1402 COPY                     3
           1404 POP_EXCEPT
           1406 RERAISE                  1

440     >> 1408 LOAD_FAST                7 (data)
           1410 LOAD_CONST              21 ('purchased')
           1412 BINARY_SUBSCR
           1422 POP_JUMP_FORWARD_IF_FALSE   232 (to 1888)

441        1424 LOAD_FAST                0 (self)
           1426 COPY                     1
           1428 LOAD_ATTR               22 (buy_count)
           1438 LOAD_CONST               2 (1)
           1440 BINARY_OP               13 (+=)
           1444 SWAP                     2
           1446 STORE_ATTR              22 (buy_count)

442        1456 LOAD_GLOBAL             33 (NULL + print)
           1468 LOAD_CONST              22 ('Bought ')
           1470 LOAD_FAST                3 (d_data)
           1472 LOAD_CONST              23 ('name')
           1474 BINARY_SUBSCR
           1484 FORMAT_VALUE             0
           1486 BUILD_STRING             2
           1488 PRECALL                  1
           1492 CALL                     1
           1502 POP_TOP

443        1504 LOAD_FAST                3 (d_data)
           1506 LOAD_CONST              23 ('name')
           1508 BINARY_SUBSCR
           1518 LOAD_FAST                0 (self)
           1520 STORE_ATTR              23 (last_bought)

444        1530 LOAD_FAST                0 (self)
           1532 LOAD_ATTR               24 (use_webhook)
           1542 POP_JUMP_FORWARD_IF_FALSE    53 (to 1650)

445        1544 LOAD_FAST                0 (self)
           1546 LOAD_ATTR               25 (webhook)
           1556 LOAD_METHOD             26 (post)
           1578 LOAD_FAST                3 (d_data)
           1580 LOAD_CONST              23 ('name')
           1582 BINARY_SUBSCR
           1592 LOAD_FAST                3 (d_data)
           1594 LOAD_CONST               3 ('price')
           1596 BINARY_SUBSCR
           1606 LOAD_FAST                3 (d_data)
           1608 LOAD_CONST              24 ('itemTargetId')
           1610 BINARY_SUBSCR
           1620 LOAD_FAST                4 (source)
           1622 LOAD_FAST                0 (self)
           1624 LOAD_ATTR               27 (version)
           1634 PRECALL                  5
           1638 CALL                     5
           1648 POP_TOP

446     >> 1650 LOAD_FAST                2 (conn)
           1652 LOAD_METHOD             12 (close)
           1674 PRECALL                  0
           1678 CALL                     0
           1688 POP_TOP

447        1690 LOAD_FAST                1 (details)
           1692 LOAD_CONST               4 ('id')
           1694 BINARY_SUBSCR
           1704 LOAD_FAST                0 (self)
           1706 LOAD_ATTR               13 (buyingids)
           1716 CONTAINS_OP              0
           1718 POP_JUMP_FORWARD_IF_FALSE    32 (to 1784)

448        1720 LOAD_FAST                0 (self)
           1722 LOAD_ATTR               13 (buyingids)
           1732 LOAD_METHOD             14 (remove)
           1754 LOAD_FAST                1 (details)
           1756 LOAD_CONST               4 ('id')
           1758 BINARY_SUBSCR
           1768 PRECALL                  1
           1772 CALL                     1
           1782 POP_TOP

449     >> 1784 NOP

459        1786 LOAD_FAST                1 (details)
           1788 LOAD_CONST               4 ('id')
           1790 BINARY_SUBSCR
           1800 LOAD_FAST                0 (self)
           1802 LOAD_ATTR               13 (buyingids)
           1812 CONTAINS_OP              0
           1814 POP_JUMP_FORWARD_IF_FALSE    34 (to 1884)

460        1816 LOAD_FAST                0 (self)
           1818 LOAD_ATTR               13 (buyingids)
           1828 LOAD_METHOD             14 (remove)
           1850 LOAD_FAST                1 (details)
           1852 LOAD_CONST               4 ('id')
           1854 BINARY_SUBSCR
           1864 PRECALL                  1
           1868 CALL                     1
           1878 POP_TOP
           1880 LOAD_CONST               0 (None)
           1882 RETURN_VALUE

459     >> 1884 LOAD_CONST               0 (None)
           1886 RETURN_VALUE

451     >> 1888 LOAD_FAST                0 (self)
           1890 COPY                     1
           1892 LOAD_ATTR               17 (error_count)
           1902 LOAD_CONST               2 (1)
           1904 BINARY_OP               13 (+=)
           1908 SWAP                     2
           1910 STORE_ATTR              17 (error_count)

452        1920 LOAD_FAST                2 (conn)
           1922 LOAD_METHOD             12 (close)
           1944 PRECALL                  0
           1948 CALL                     0
           1958 POP_TOP

453        1960 LOAD_FAST                1 (details)
           1962 LOAD_CONST               4 ('id')
           1964 BINARY_SUBSCR
           1974 LOAD_FAST                0 (self)
           1976 LOAD_ATTR               13 (buyingids)
           1986 CONTAINS_OP              0
           1988 POP_JUMP_FORWARD_IF_FALSE    32 (to 2054)

454        1990 LOAD_FAST                0 (self)
           1992 LOAD_ATTR               13 (buyingids)
           2002 LOAD_METHOD             14 (remove)
           2024 LOAD_FAST                1 (details)
           2026 LOAD_CONST               4 ('id')
           2028 BINARY_SUBSCR
           2038 PRECALL                  1
           2042 CALL                     1
           2052 POP_TOP

455     >> 2054 NOP

459        2056 LOAD_FAST                1 (details)
           2058 LOAD_CONST               4 ('id')
           2060 BINARY_SUBSCR
           2070 LOAD_FAST                0 (self)
           2072 LOAD_ATTR               13 (buyingids)
           2082 CONTAINS_OP              0
           2084 POP_JUMP_FORWARD_IF_FALSE    34 (to 2154)

460        2086 LOAD_FAST                0 (self)
           2088 LOAD_ATTR               13 (buyingids)
           2098 LOAD_METHOD             14 (remove)
           2120 LOAD_FAST                1 (details)
           2122 LOAD_CONST               4 ('id')
           2124 BINARY_SUBSCR
           2134 PRECALL                  1
           2138 CALL                     1
           2148 POP_TOP
           2150 LOAD_CONST               0 (None)
           2152 RETURN_VALUE

459     >> 2154 LOAD_CONST               0 (None)
           2156 RETURN_VALUE
        >> 2158 PUSH_EXC_INFO

456        2160 LOAD_GLOBAL             56 (Exception)
           2172 CHECK_EXC_MATCH
           2174 POP_JUMP_FORWARD_IF_FALSE    30 (to 2236)
           2176 STORE_FAST               8 (ex)

457        2178 LOAD_FAST                2 (conn)
           2180 LOAD_METHOD             12 (close)
           2202 PRECALL                  0
           2206 CALL                     0
           2216 POP_TOP
           2218 POP_EXCEPT
           2220 LOAD_CONST               0 (None)
           2222 STORE_FAST               8 (ex)
           2224 DELETE_FAST              8 (ex)
           2226 JUMP_FORWARD             8 (to 2244)
        >> 2228 LOAD_CONST               0 (None)
           2230 STORE_FAST               8 (ex)
           2232 DELETE_FAST              8 (ex)
           2234 RERAISE                  1

456     >> 2236 RERAISE                  0
        >> 2238 COPY                     3
           2240 POP_EXCEPT
           2242 RERAISE                  1

457     >> 2244 NOP

459        2246 LOAD_FAST                1 (details)
           2248 LOAD_CONST               4 ('id')
           2250 BINARY_SUBSCR
           2260 LOAD_FAST                0 (self)
           2262 LOAD_ATTR               13 (buyingids)
           2272 CONTAINS_OP              0
           2274 POP_JUMP_FORWARD_IF_FALSE    34 (to 2344)

460        2276 LOAD_FAST                0 (self)
           2278 LOAD_ATTR               13 (buyingids)
           2288 LOAD_METHOD             14 (remove)
           2310 LOAD_FAST                1 (details)
           2312 LOAD_CONST               4 ('id')
           2314 BINARY_SUBSCR
           2324 PRECALL                  1
           2328 CALL                     1
           2338 POP_TOP
           2340 LOAD_CONST               0 (None)
           2342 RETURN_VALUE

459     >> 2344 LOAD_CONST               0 (None)
           2346 RETURN_VALUE
        >> 2348 PUSH_EXC_INFO
           2350 LOAD_FAST                1 (details)
           2352 LOAD_CONST               4 ('id')
           2354 BINARY_SUBSCR
           2364 LOAD_FAST                0 (self)
           2366 LOAD_ATTR               13 (buyingids)
           2376 CONTAINS_OP              0
           2378 POP_JUMP_FORWARD_IF_FALSE    33 (to 2446)

460        2380 LOAD_FAST                0 (self)
           2382 LOAD_ATTR               13 (buyingids)
           2392 LOAD_METHOD             14 (remove)
           2414 LOAD_FAST                1 (details)
           2416 LOAD_CONST               4 ('id')
           2418 BINARY_SUBSCR
           2428 PRECALL                  1
           2432 CALL                     1
           2442 POP_TOP
           2444 RERAISE                  0

459     >> 2446 RERAISE                  0
        >> 2448 COPY                     3
           2450 POP_EXCEPT
           2452 RERAISE                  1
ExceptionTable:
  220 to 386 -> 2158 [0]
  390 to 428 -> 432 [0]
  430 to 430 -> 2158 [0]
  432 to 604 -> 712 [1] lasti
  606 to 606 -> 2158 [0]
  710 to 710 -> 712 [1] lasti
  712 to 974 -> 2158 [0]
  1082 to 1156 -> 1160 [0]
  1158 to 1158 -> 2158 [0]
  1160 to 1296 -> 1402 [1] lasti
  1298 to 1298 -> 2158 [0]
  1402 to 1782 -> 2158 [0]
  1888 to 2052 -> 2158 [0]
  2158 to 2176 -> 2238 [1] lasti
  2178 to 2216 -> 2228 [1] lasti
  2218 to 2226 -> 2348 [0]
  2228 to 2236 -> 2238 [1] lasti
  2238 to 2242 -> 2348 [0]
  2348 to 2446 -> 2448 [1] lasti

Disassembly of <code object ensure_connection at 0x000001E6603093B0, file "main.py", line 463>:
463           0 RESUME                   0

464           2 NOP

465     >>    4 LOAD_FAST                0 (self)
              6 LOAD_ATTR                0 (auto_socket)
             16 LOAD_ATTR                1 (connected)
             26 LOAD_CONST               2 (False)
             28 COMPARE_OP               2 (==)
             34 POP_JUMP_FORWARD_IF_FALSE   127 (to 290)

466          36 LOAD_GLOBAL              5 (NULL + print)
             48 LOAD_CONST               3 ('connecting')
             50 PRECALL                  1
             54 CALL                     1
             64 POP_TOP

467          66 NOP

468          68 LOAD_FAST                0 (self)
             70 LOAD_ATTR                0 (auto_socket)
             80 LOAD_METHOD              3 (disconnect)
            102 PRECALL                  0
            106 CALL                     0
            116 POP_TOP

469         118 LOAD_FAST                0 (self)
            120 LOAD_ATTR                0 (auto_socket)
            130 LOAD_METHOD              4 (connect)
            152 LOAD_GLOBAL             10 (uri)
            164 LOAD_CONST               4 (10)
            166 LOAD_CONST               5 ('key')
            168 LOAD_GLOBAL             12 (settings)
            180 LOAD_CONST               6 ('KEY')
            182 BINARY_SUBSCR
            192 BUILD_MAP                1
            194 KW_NAMES                 7
            196 PRECALL                  3
            200 CALL                     3
            210 POP_TOP
            212 JUMP_FORWARD            38 (to 290)
        >>  214 PUSH_EXC_INFO

470         216 LOAD_GLOBAL             14 (Exception)
            228 CHECK_EXC_MATCH
            230 POP_JUMP_FORWARD_IF_FALSE    25 (to 282)
            232 STORE_FAST               1 (e)

471         234 LOAD_GLOBAL              5 (NULL + print)
            246 LOAD_FAST                1 (e)
            248 PRECALL                  1
            252 CALL                     1
            262 POP_TOP
            264 POP_EXCEPT
            266 LOAD_CONST               0 (None)
            268 STORE_FAST               1 (e)
            270 DELETE_FAST              1 (e)
            272 JUMP_FORWARD             8 (to 290)
        >>  274 LOAD_CONST               0 (None)
            276 STORE_FAST               1 (e)
            278 DELETE_FAST              1 (e)
            280 RERAISE                  1

470     >>  282 RERAISE                  0
        >>  284 COPY                     3
            286 POP_EXCEPT
            288 RERAISE                  1

472     >>  290 LOAD_GLOBAL             17 (NULL + time)
            302 LOAD_ATTR                9 (sleep)
            312 LOAD_CONST               8 (1)
            314 PRECALL                  1
            318 CALL                     1
            328 POP_TOP

464         330 JUMP_BACKWARD          164 (to 4)
ExceptionTable:
  68 to 210 -> 214 [0]
  214 to 232 -> 284 [1] lasti
  234 to 262 -> 274 [1] lasti
  274 to 282 -> 284 [1] lasti

Disassembly of <code object auto_search at 0x000001E65FE44AB0, file "main.py", line 474>:
              0 MAKE_CELL                0 (self)

474           2 RESUME                   0

475           4 LOAD_DEREF               0 (self)
              6 LOAD_ATTR                0 (auto_socket)
             16 LOAD_METHOD              1 (connect)
             38 LOAD_GLOBAL              4 (uri)
             50 LOAD_CONST               1 (10)
             52 LOAD_CONST               2 ('key')
             54 LOAD_GLOBAL              6 (settings)
             66 LOAD_CONST               3 ('KEY')
             68 BINARY_SUBSCR
             78 BUILD_MAP                1
             80 KW_NAMES                 4
             82 PRECALL                  3
             86 CALL                     3
             96 POP_TOP

476          98 LOAD_GLOBAL              9 (NULL + threading)
            110 LOAD_ATTR                5 (Thread)
            120 LOAD_DEREF               0 (self)
            122 LOAD_ATTR                6 (ensure_connection)
            132 KW_NAMES                 5
            134 PRECALL                  1
            138 CALL                     1
            148 LOAD_METHOD              7 (start)
            170 PRECALL                  0
            174 CALL                     0
            184 POP_TOP

478         186 LOAD_DEREF               0 (self)
            188 LOAD_ATTR                0 (auto_socket)
            198 LOAD_METHOD              8 (on)
            220 LOAD_CONST               6 ('freelimited')
            222 PRECALL                  1
            226 CALL                     1

479         236 LOAD_CLOSURE             0 (self)
            238 BUILD_TUPLE              1
            240 LOAD_CONST               7 (<code object message at 0x000001E6603098C0, file "main.py", line 478>)
            242 MAKE_FUNCTION            8 (closure)

478         244 PRECALL                  0
            248 CALL                     0

479         258 STORE_FAST               1 (message)
            260 LOAD_CONST               0 (None)
            262 RETURN_VALUE

Disassembly of <code object message at 0x000001E6603098C0, file "main.py", line 478>:
              0 COPY_FREE_VARS           1

478           2 RESUME                   0

480           4 LOAD_GLOBAL              1 (NULL + print)
             16 LOAD_CONST               1 ('Autosearch detected: ')
             18 LOAD_FAST                0 (item)
             20 LOAD_CONST               2 ('name')
             22 BINARY_SUBSCR
             32 FORMAT_VALUE             0
             34 BUILD_STRING             2
             36 PRECALL                  1
             40 CALL                     1
             50 POP_TOP

481          52 LOAD_FAST                0 (item)
             54 LOAD_CONST               3 ('id')
             56 BINARY_SUBSCR
             66 LOAD_DEREF               5 (self)
             68 LOAD_ATTR                1 (buyingids)
             78 CONTAINS_OP              1
             80 EXTENDED_ARG             1
             82 POP_JUMP_FORWARD_IF_FALSE   310 (to 704)
             84 LOAD_FAST                0 (item)
             86 LOAD_CONST               3 ('id')
             88 BINARY_SUBSCR
             98 LOAD_DEREF               5 (self)
            100 LOAD_ATTR                2 (blacklist)
            110 CONTAINS_OP              1
            112 EXTENDED_ARG             1
            114 POP_JUMP_FORWARD_IF_FALSE   296 (to 708)
            116 LOAD_FAST                0 (item)
            118 LOAD_CONST               4 ('price')
            120 BINARY_SUBSCR
            130 LOAD_CONST               5 (0)
            132 COMPARE_OP               1 (<=)
            138 EXTENDED_ARG             1
            140 POP_JUMP_FORWARD_IF_FALSE   285 (to 712)

482         142 LOAD_DEREF               5 (self)
            144 LOAD_ATTR                3 (auto_search_buy)
            154 LOAD_METHOD              4 (get)
            176 PRECALL                  0
            180 CALL                     0
            190 STORE_FAST               1 (conn)

483         192 LOAD_FAST                1 (conn)
            194 LOAD_METHOD              5 (request)

484         216 LOAD_CONST               6 ('POST')

485         218 LOAD_CONST               7 ('/marketplace-items/v1/items/details')

486         220 LOAD_CONST               8 ('{"itemIds":["%s"]}')
            222 LOAD_FAST                0 (item)
            224 LOAD_CONST               9 ('collectibleItemId')
            226 BINARY_SUBSCR
            236 BINARY_OP                6 (%)

487         240 LOAD_CONST              10 ('application/json')
            242 LOAD_CONST              11 ('.ROBLOSECURITY=%s')
            244 LOAD_DEREF               5 (self)
            246 LOAD_ATTR                6 (buyer_cookie)
            256 LOAD_CONST              12 ('cookie')
            258 BINARY_SUBSCR
            268 BINARY_OP                6 (%)
            272 LOAD_DEREF               5 (self)
            274 LOAD_ATTR                6 (buyer_cookie)
            284 LOAD_CONST              13 ('auth')
            286 BINARY_SUBSCR
            296 LOAD_CONST              14 (('Content-Type', 'Cookie', 'x-csrf-token'))
            298 BUILD_CONST_KEY_MAP      3

483         300 KW_NAMES                15
            302 PRECALL                  4
            306 CALL                     4
            316 POP_TOP

489         318 LOAD_FAST                1 (conn)
            320 LOAD_METHOD              7 (getresponse)
            342 PRECALL                  0
            346 CALL                     0
            356 STORE_FAST               2 (resp)

490         358 LOAD_GLOBAL             17 (NULL + json)
            370 LOAD_ATTR                9 (loads)
            380 LOAD_FAST                2 (resp)
            382 LOAD_METHOD             10 (read)
            404 PRECALL                  0
            408 CALL                     0
            418 PRECALL                  1
            422 CALL                     1
            432 LOAD_CONST               5 (0)
            434 BINARY_SUBSCR
            444 STORE_FAST               3 (data)

491         446 LOAD_DEREF               5 (self)
            448 LOAD_ATTR                1 (buyingids)
            458 LOAD_METHOD             11 (append)
            480 LOAD_FAST                0 (item)
            482 LOAD_CONST               3 ('id')
            484 BINARY_SUBSCR
            494 PRECALL                  1
            498 CALL                     1
            508 POP_TOP

492         510 LOAD_GLOBAL             25 (NULL + range)
            522 LOAD_CONST              16 (6)
            524 PRECALL                  1
            528 CALL                     1
            538 GET_ITER
        >>  540 FOR_ITER                87 (to 716)
            542 STORE_FAST               4 (_)

493         544 LOAD_GLOBAL             27 (NULL + time)
            556 LOAD_ATTR               14 (sleep)
            566 LOAD_CONST              17 (0.1)
            568 PRECALL                  1
            572 CALL                     1
            582 POP_TOP

494         584 LOAD_DEREF               5 (self)
            586 LOAD_ATTR               15 (auto_buy_pool)
            596 GET_ITER
        >>  598 FOR_ITER                51 (to 702)
            600 STORE_FAST               1 (conn)

495         602 LOAD_GLOBAL             33 (NULL + threading)
            614 LOAD_ATTR               17 (Thread)
            624 LOAD_DEREF               5 (self)
            626 LOAD_ATTR               18 (buy_item)
            636 LOAD_FAST                0 (item)
            638 LOAD_FAST                1 (conn)
            640 LOAD_FAST                3 (data)
            642 LOAD_CONST              18 ('autosearch')
            644 BUILD_TUPLE              4
            646 KW_NAMES                19
            648 PRECALL                  2
            652 CALL                     2
            662 LOAD_METHOD             19 (start)
            684 PRECALL                  0
            688 CALL                     0
            698 POP_TOP
            700 JUMP_BACKWARD           52 (to 598)

494     >>  702 JUMP_BACKWARD           82 (to 540)

481     >>  704 LOAD_CONST               0 (None)
            706 RETURN_VALUE
        >>  708 LOAD_CONST               0 (None)
            710 RETURN_VALUE
        >>  712 LOAD_CONST               0 (None)
            714 RETURN_VALUE

492     >>  716 LOAD_CONST               0 (None)
            718 RETURN_VALUE

Disassembly of <code object post_free_item at 0x000001E660028030, file "main.py", line 497>:
497           0 RESUME                   0

498           2 LOAD_GLOBAL              1 (NULL + requests)
             14 LOAD_ATTR                1 (session)
             24 PRECALL                  0
             28 CALL                     0
             38 BEFORE_WITH
             40 STORE_FAST               2 (session)

500          42 LOAD_GLOBAL              4 (settings)
             54 LOAD_CONST               1 ('KEY')
             56 BINARY_SUBSCR

501          66 LOAD_FAST                1 (item)

499          68 LOAD_CONST               2 (('key', 'item'))
             70 BUILD_CONST_KEY_MAP      2
             72 STORE_FAST               3 (payload)

503          74 LOAD_FAST                2 (session)
             76 LOAD_METHOD              3 (post)
             98 LOAD_GLOBAL              8 (uri)
            110 FORMAT_VALUE             0
            112 LOAD_CONST               3 ('/clientautosearch')
            114 BUILD_STRING             2
            116 LOAD_FAST                3 (payload)
            118 KW_NAMES                 4
            120 PRECALL                  2
            124 CALL                     2
            134 POP_TOP

498         136 LOAD_CONST               0 (None)
            138 LOAD_CONST               0 (None)
            140 LOAD_CONST               0 (None)
            142 PRECALL                  2
            146 CALL                     2
            156 POP_TOP
            158 LOAD_CONST               0 (None)
            160 RETURN_VALUE
        >>  162 PUSH_EXC_INFO
            164 WITH_EXCEPT_START
            166 POP_JUMP_FORWARD_IF_TRUE     4 (to 176)
            168 RERAISE                  2
        >>  170 COPY                     3
            172 POP_EXCEPT
            174 RERAISE                  1
        >>  176 POP_TOP
            178 POP_EXCEPT
            180 POP_TOP
            182 POP_TOP
            184 LOAD_CONST               0 (None)
            186 RETURN_VALUE
ExceptionTable:
  40 to 134 -> 162 [1] lasti
  162 to 168 -> 170 [3] lasti
  176 to 176 -> 170 [3] lasti

Disassembly of <code object watch_items_proxy at 0x000001E66030AF60, file "main.py", line 505>:
505           0 RESUME                   0

506     >>    2 NOP

507     >>    4 LOAD_GLOBAL              1 (NULL + len)
             16 LOAD_FAST                0 (self)
             18 LOAD_ATTR                1 (watch_items_payload)
             28 PRECALL                  1
             32 CALL                     1
             42 LOAD_CONST               2 (0)
             44 COMPARE_OP               2 (==)
             50 POP_JUMP_FORWARD_IF_FALSE     1 (to 54)

508          52 JUMP_BACKWARD           26 (to 2)

509     >>   54 NOP

510          56 LOAD_GLOBAL              5 (NULL + time)
             68 LOAD_ATTR                2 (time)
             78 PRECALL                  0
             82 CALL                     0
             92 STORE_FAST               1 (start_time)

512          94 LOAD_GLOBAL              7 (NULL + requests)
            106 LOAD_ATTR                4 (session)
            116 PRECALL                  0
            120 CALL                     0
            130 BEFORE_WITH
            132 STORE_FAST               2 (session)

513         134 LOAD_GLOBAL             11 (NULL + random)
            146 LOAD_ATTR                6 (choice)
            156 LOAD_FAST                0 (self)
            158 LOAD_ATTR                7 (proxy_pool)
            168 PRECALL                  1
            172 CALL                     1
            182 STORE_FAST               3 (proxy)

515         184 LOAD_FAST                3 (proxy)
            186 LOAD_ATTR                8 (url)

516         196 LOAD_FAST                3 (proxy)
            198 LOAD_ATTR                8 (url)

514         208 LOAD_CONST               3 (('http', 'https'))
            210 BUILD_CONST_KEY_MAP      2
            212 LOAD_FAST                2 (session)
            214 STORE_ATTR               9 (proxies)

519         224 LOAD_CONST               4 ('x-csrf-token')
            226 LOAD_FAST                3 (proxy)
            228 LOAD_ATTR               10 (auth)

518         238 BUILD_MAP                1
            240 STORE_FAST               4 (headers)

521         242 LOAD_FAST                2 (session)
            244 LOAD_METHOD             11 (post)
            266 LOAD_CONST               5 ('https://catalog.roblox.com/v1/catalog/items/details')
            268 LOAD_CONST               6 ('items')
            270 LOAD_FAST                0 (self)
            272 LOAD_ATTR                1 (watch_items_payload)
            282 BUILD_MAP                1
            284 LOAD_FAST                4 (headers)
            286 LOAD_CONST               7 (False)
            288 KW_NAMES                 8
            290 PRECALL                  4
            294 CALL                     4
            304 STORE_FAST               5 (conn)

522         306 LOAD_FAST                5 (conn)
            308 LOAD_METHOD             12 (json)
            330 PRECALL                  0
            334 CALL                     0
            344 STORE_FAST               6 (data)

523         346 LOAD_FAST                5 (conn)
            348 LOAD_ATTR               13 (status_code)
            358 LOAD_CONST               9 (200)
            360 COMPARE_OP               2 (==)
            366 EXTENDED_ARG             1
            368 POP_JUMP_FORWARD_IF_FALSE   424 (to 1218)

524         370 LOAD_FAST                0 (self)
            372 COPY                     1
            374 LOAD_ATTR               14 (proxy_check_count)
            384 LOAD_CONST              10 (1)
            386 BINARY_OP               13 (+=)
            390 SWAP                     2
            392 STORE_ATTR              14 (proxy_check_count)

526         402 LOAD_FAST                6 (data)
            404 LOAD_CONST              11 ('data')
            406 BINARY_SUBSCR
            416 EXTENDED_ARG             1
            418 POP_JUMP_FORWARD_IF_FALSE   398 (to 1216)

527         420 LOAD_FAST                6 (data)
            422 LOAD_CONST              11 ('data')
            424 BINARY_SUBSCR
            434 GET_ITER
        >>  436 EXTENDED_ARG             1
            438 FOR_ITER               388 (to 1216)
            440 STORE_FAST               7 (item)

528         442 LOAD_CONST              12 ('unitsAvailableForConsumption')
            444 LOAD_FAST                7 (item)
            446 CONTAINS_OP              0
            448 EXTENDED_ARG             1
            450 POP_JUMP_FORWARD_IF_FALSE   380 (to 1212)
            452 LOAD_FAST                7 (item)
            454 LOAD_CONST              12 ('unitsAvailableForConsumption')
            456 BINARY_SUBSCR
            466 LOAD_CONST               2 (0)
            468 COMPARE_OP               4 (>)
            474 EXTENDED_ARG             1
            476 POP_JUMP_FORWARD_IF_FALSE   367 (to 1212)
            478 LOAD_FAST                7 (item)
            480 LOAD_CONST              13 ('id')
            482 BINARY_SUBSCR
            492 LOAD_FAST                0 (self)
            494 LOAD_ATTR               15 (buyingids)
            504 CONTAINS_OP              1
            506 EXTENDED_ARG             1
            508 POP_JUMP_FORWARD_IF_FALSE   351 (to 1212)
            510 LOAD_FAST                7 (item)
            512 LOAD_CONST              13 ('id')
            514 BINARY_SUBSCR
            524 LOAD_FAST                0 (self)
            526 LOAD_ATTR               16 (blacklist)
            536 CONTAINS_OP              1
            538 EXTENDED_ARG             1
            540 POP_JUMP_FORWARD_IF_FALSE   335 (to 1212)

529         542 LOAD_FAST                7 (item)
            544 LOAD_CONST              14 ('price')
            546 BINARY_SUBSCR
            556 LOAD_CONST               2 (0)
            558 COMPARE_OP               4 (>)
            564 POP_JUMP_FORWARD_IF_FALSE     8 (to 582)
            566 LOAD_FAST                0 (self)
            568 LOAD_ATTR               17 (buy_only_free)
            578 POP_JUMP_FORWARD_IF_FALSE     1 (to 582)

530         580 JUMP_BACKWARD           73 (to 436)

532     >>  582 NOP

533         584 LOAD_FAST                0 (self)
            586 LOAD_ATTR               18 (single_buy)
            596 LOAD_METHOD             19 (get)
            618 PRECALL                  0
            622 CALL                     0
            632 STORE_FAST               8 (d_conn)

534         634 LOAD_FAST                8 (d_conn)
            636 LOAD_METHOD             20 (request)

535         658 LOAD_CONST              15 ('POST')

536         660 LOAD_CONST              16 ('/marketplace-items/v1/items/details')

537         662 LOAD_CONST              17 ('{"itemIds":["%s"]}')
            664 LOAD_FAST                7 (item)
            666 LOAD_CONST              18 ('collectibleItemId')
            668 BINARY_SUBSCR
            678 BINARY_OP                6 (%)

538         682 LOAD_CONST              19 ('application/json')
            684 LOAD_CONST              20 ('.ROBLOSECURITY=%s')
            686 LOAD_FAST                0 (self)
            688 LOAD_ATTR               21 (buyer_cookie)
            698 LOAD_CONST              21 ('cookie')
            700 BINARY_SUBSCR
            710 BINARY_OP                6 (%)
            714 LOAD_FAST                0 (self)
            716 LOAD_ATTR               21 (buyer_cookie)
            726 LOAD_CONST              22 ('auth')
            728 BINARY_SUBSCR
            738 LOAD_CONST              23 (('Content-Type', 'Cookie', 'x-csrf-token'))
            740 BUILD_CONST_KEY_MAP      3

534         742 KW_NAMES                24
            744 PRECALL                  4
            748 CALL                     4
            758 POP_TOP

540         760 LOAD_FAST                8 (d_conn)
            762 LOAD_METHOD             22 (getresponse)
            784 PRECALL                  0
            788 CALL                     0
            798 STORE_FAST               9 (d_resp)

541         800 LOAD_GLOBAL             25 (NULL + json)
            812 LOAD_ATTR               23 (loads)
            822 LOAD_FAST                9 (d_resp)
            824 LOAD_METHOD             24 (read)
            846 PRECALL                  0
            850 CALL                     0
            860 PRECALL                  1
            864 CALL                     1
            874 LOAD_CONST               2 (0)
            876 BINARY_SUBSCR
            886 STORE_FAST              10 (d_data)

542         888 LOAD_FAST                0 (self)
            890 LOAD_ATTR               15 (buyingids)
            900 LOAD_METHOD             25 (append)
            922 LOAD_FAST                7 (item)
            924 LOAD_CONST              13 ('id')
            926 BINARY_SUBSCR
            936 PRECALL                  1
            940 CALL                     1
            950 POP_TOP

543         952 LOAD_FAST                0 (self)
            954 LOAD_ATTR               26 (item_pool)
            964 LOAD_FAST                7 (item)
            966 LOAD_CONST              13 ('id')
            968 BINARY_SUBSCR
            978 BINARY_SUBSCR
            988 GET_ITER
        >>  990 FOR_ITER                51 (to 1094)
            992 STORE_FAST               5 (conn)

544         994 LOAD_GLOBAL             55 (NULL + threading)
           1006 LOAD_ATTR               28 (Thread)
           1016 LOAD_FAST                0 (self)
           1018 LOAD_ATTR               29 (buy_item)
           1028 LOAD_FAST                7 (item)
           1030 LOAD_FAST                5 (conn)
           1032 LOAD_FAST               10 (d_data)
           1034 LOAD_CONST              25 ('proxied watcher')
           1036 BUILD_TUPLE              4
           1038 KW_NAMES                26
           1040 PRECALL                  2
           1044 CALL                     2
           1054 LOAD_METHOD             30 (start)
           1076 PRECALL                  0
           1080 CALL                     0
           1090 POP_TOP
           1092 JUMP_BACKWARD           52 (to 990)

545     >> 1094 LOAD_FAST                7 (item)
           1096 LOAD_CONST              14 ('price')
           1098 BINARY_SUBSCR
           1108 LOAD_CONST               2 (0)
           1110 COMPARE_OP               1 (<=)
           1116 POP_JUMP_FORWARD_IF_FALSE    21 (to 1160)

546        1118 LOAD_FAST                0 (self)
           1120 LOAD_METHOD             31 (post_free_item)
           1142 LOAD_FAST                7 (item)
           1144 PRECALL                  1
           1148 CALL                     1
           1158 POP_TOP
        >> 1160 EXTENDED_ARG             1
           1162 JUMP_BACKWARD          364 (to 436)
        >> 1164 PUSH_EXC_INFO

547        1166 POP_TOP

548        1168 LOAD_FAST                0 (self)
           1170 COPY                     1
           1172 LOAD_ATTR               32 (error_count)
           1182 LOAD_CONST              10 (1)
           1184 BINARY_OP               13 (+=)
           1188 SWAP                     2
           1190 STORE_ATTR              32 (error_count)
           1200 POP_EXCEPT
           1202 EXTENDED_ARG             1
           1204 JUMP_BACKWARD          385 (to 436)
        >> 1206 COPY                     3
           1208 POP_EXCEPT
           1210 RERAISE                  1
        >> 1212 EXTENDED_ARG             1
           1214 JUMP_BACKWARD          390 (to 436)
        >> 1216 JUMP_FORWARD            49 (to 1316)

549     >> 1218 LOAD_FAST                5 (conn)
           1220 LOAD_ATTR               13 (status_code)
           1230 LOAD_CONST              27 (403)
           1232 COMPARE_OP               2 (==)
           1238 POP_JUMP_FORWARD_IF_FALSE    22 (to 1284)

550        1240 LOAD_FAST                0 (self)
           1242 LOAD_METHOD             33 (load_proxy)
           1264 LOAD_FAST                3 (proxy)
           1266 PRECALL                  1
           1270 CALL                     1
           1280 POP_TOP
           1282 JUMP_FORWARD            16 (to 1316)

552     >> 1284 LOAD_FAST                0 (self)
           1286 COPY                     1
           1288 LOAD_ATTR               34 (proxy_error_count)
           1298 LOAD_CONST              10 (1)
           1300 BINARY_OP               13 (+=)
           1304 SWAP                     2
           1306 STORE_ATTR              34 (proxy_error_count)

512     >> 1316 LOAD_CONST               0 (None)
           1318 LOAD_CONST               0 (None)
           1320 LOAD_CONST               0 (None)
           1322 PRECALL                  2
           1326 CALL                     2
           1336 POP_TOP
           1338 JUMP_FORWARD            11 (to 1362)
        >> 1340 PUSH_EXC_INFO
           1342 WITH_EXCEPT_START
           1344 POP_JUMP_FORWARD_IF_TRUE     4 (to 1354)
           1346 RERAISE                  2
        >> 1348 COPY                     3
           1350 POP_EXCEPT
           1352 RERAISE                  1
        >> 1354 POP_TOP
           1356 POP_EXCEPT
           1358 POP_TOP
           1360 POP_TOP

553     >> 1362 LOAD_GLOBAL              5 (NULL + time)
           1374 LOAD_ATTR                2 (time)
           1384 PRECALL                  0
           1388 CALL                     0
           1398 STORE_FAST              11 (end_time)

554        1400 LOAD_GLOBAL             71 (NULL + round)
           1412 LOAD_FAST               11 (end_time)
           1414 LOAD_FAST                1 (start_time)
           1416 BINARY_OP               10 (-)
           1420 LOAD_CONST              28 (2)
           1422 PRECALL                  2
           1426 CALL                     2
           1436 LOAD_FAST                0 (self)
           1438 STORE_ATTR              36 (proxy_speed_count)
           1448 JUMP_FORWARD            54 (to 1558)
        >> 1450 PUSH_EXC_INFO

555        1452 LOAD_GLOBAL             74 (Exception)
           1464 CHECK_EXC_MATCH
           1466 POP_JUMP_FORWARD_IF_FALSE    41 (to 1550)
           1468 STORE_FAST              12 (error)

556        1470 LOAD_FAST                0 (self)
           1472 COPY                     1
           1474 LOAD_ATTR               34 (proxy_error_count)
           1484 LOAD_CONST              10 (1)
           1486 BINARY_OP               13 (+=)
           1490 SWAP                     2
           1492 STORE_ATTR              34 (proxy_error_count)

557        1502 LOAD_GLOBAL             77 (NULL + print)
           1514 LOAD_FAST               12 (error)
           1516 PRECALL                  1
           1520 CALL                     1
           1530 POP_TOP

558        1532 POP_EXCEPT
           1534 LOAD_CONST               0 (None)
           1536 STORE_FAST              12 (error)
           1538 DELETE_FAST             12 (error)
           1540 JUMP_FORWARD             8 (to 1558)
        >> 1542 LOAD_CONST               0 (None)
           1544 STORE_FAST              12 (error)
           1546 DELETE_FAST             12 (error)
           1548 RERAISE                  1

555     >> 1550 RERAISE                  0
        >> 1552 COPY                     3
           1554 POP_EXCEPT
           1556 RERAISE                  1

559     >> 1558 LOAD_GLOBAL              5 (NULL + time)
           1570 LOAD_ATTR               39 (sleep)
           1580 LOAD_FAST                0 (self)
           1582 LOAD_ATTR               40 (proxy_scan_speed)
           1592 PRECALL                  1
           1596 CALL                     1
           1606 POP_TOP

506        1608 EXTENDED_ARG             3
           1610 JUMP_BACKWARD          804 (to 4)
ExceptionTable:
  56 to 130 -> 1450 [0]
  132 to 580 -> 1340 [1] lasti
  584 to 1158 -> 1164 [2]
  1160 to 1162 -> 1340 [1] lasti
  1164 to 1198 -> 1206 [3] lasti
  1200 to 1314 -> 1340 [1] lasti
  1316 to 1338 -> 1450 [0]
  1340 to 1346 -> 1348 [3] lasti
  1348 to 1352 -> 1450 [0]
  1354 to 1354 -> 1348 [3] lasti
  1356 to 1446 -> 1450 [0]
  1450 to 1468 -> 1552 [1] lasti
  1470 to 1530 -> 1542 [1] lasti
  1542 to 1550 -> 1552 [1] lasti

Disassembly of <code object watch_items at 0x000001E66030B670, file "main.py", line 561>:
561           0 RESUME                   0

562           2 LOAD_FAST                0 (self)
              4 LOAD_ATTR                0 (details_cookie)
             14 STORE_FAST               1 (cookie)

564     >>   16 NOP

565     >>   18 LOAD_GLOBAL              3 (NULL + len)
             30 LOAD_FAST                0 (self)
             32 LOAD_ATTR                2 (watch_items_payload)
             42 PRECALL                  1
             46 CALL                     1
             56 LOAD_CONST               2 (0)
             58 COMPARE_OP               2 (==)
             64 POP_JUMP_FORWARD_IF_FALSE     1 (to 68)

566          66 JUMP_BACKWARD           26 (to 16)

567     >>   68 NOP

568          70 LOAD_GLOBAL              7 (NULL + time)
             82 LOAD_ATTR                3 (time)
             92 PRECALL                  0
             96 CALL                     0
            106 STORE_FAST               2 (start_time)

570         108 LOAD_GLOBAL              9 (NULL + requests)
            120 LOAD_ATTR                5 (session)
            130 PRECALL                  0
            134 CALL                     0
            144 BEFORE_WITH
            146 STORE_FAST               3 (session)

572         148 LOAD_CONST               3 ('x-csrf-token')
            150 LOAD_FAST                1 (cookie)
            152 LOAD_CONST               4 ('auth')
            154 BINARY_SUBSCR

571         164 BUILD_MAP                1
            166 STORE_FAST               4 (headers)

574         168 LOAD_FAST                1 (cookie)
            170 LOAD_CONST               5 ('cookie')
            172 BINARY_SUBSCR
            182 LOAD_FAST                3 (session)
            184 LOAD_ATTR                6 (cookies)
            194 LOAD_CONST               6 ('.ROBLOSECURITY')
            196 STORE_SUBSCR

575         200 LOAD_FAST                3 (session)
            202 LOAD_METHOD              7 (post)
            224 LOAD_CONST               7 ('https://catalog.roblox.com/v1/catalog/items/details')
            226 LOAD_CONST               8 ('items')
            228 LOAD_FAST                0 (self)
            230 LOAD_ATTR                2 (watch_items_payload)
            240 BUILD_MAP                1
            242 LOAD_FAST                4 (headers)
            244 LOAD_CONST               9 (False)
            246 KW_NAMES                10
            248 PRECALL                  4
            252 CALL                     4
            262 STORE_FAST               5 (conn)

576         264 LOAD_FAST                5 (conn)
            266 LOAD_METHOD              8 (json)
            288 PRECALL                  0
            292 CALL                     0
            302 STORE_FAST               6 (data)

577         304 LOAD_FAST                5 (conn)
            306 LOAD_ATTR                9 (status_code)
            316 LOAD_CONST              11 (200)
            318 COMPARE_OP               2 (==)
            324 EXTENDED_ARG             1
            326 POP_JUMP_FORWARD_IF_FALSE   397 (to 1122)

578         328 LOAD_FAST                0 (self)
            330 COPY                     1
            332 LOAD_ATTR               10 (check_count)
            342 LOAD_CONST              12 (1)
            344 BINARY_OP               13 (+=)
            348 SWAP                     2
            350 STORE_ATTR              10 (check_count)

580         360 LOAD_FAST                6 (data)
            362 LOAD_CONST              13 ('data')
            364 BINARY_SUBSCR
            374 EXTENDED_ARG             1
            376 POP_JUMP_FORWARD_IF_FALSE   371 (to 1120)

581         378 LOAD_FAST                6 (data)
            380 LOAD_CONST              13 ('data')
            382 BINARY_SUBSCR
            392 GET_ITER
        >>  394 EXTENDED_ARG             1
            396 FOR_ITER               361 (to 1120)
            398 STORE_FAST               7 (item)

582         400 LOAD_CONST              14 ('unitsAvailableForConsumption')
            402 LOAD_FAST                7 (item)
            404 CONTAINS_OP              0
            406 EXTENDED_ARG             1
            408 POP_JUMP_FORWARD_IF_FALSE   353 (to 1116)
            410 LOAD_FAST                7 (item)
            412 LOAD_CONST              14 ('unitsAvailableForConsumption')
            414 BINARY_SUBSCR
            424 LOAD_CONST               2 (0)
            426 COMPARE_OP               4 (>)
            432 EXTENDED_ARG             1
            434 POP_JUMP_FORWARD_IF_FALSE   340 (to 1116)
            436 LOAD_FAST                7 (item)
            438 LOAD_CONST              15 ('id')
            440 BINARY_SUBSCR
            450 LOAD_FAST                0 (self)
            452 LOAD_ATTR               11 (buyingids)
            462 CONTAINS_OP              1
            464 EXTENDED_ARG             1
            466 POP_JUMP_FORWARD_IF_FALSE   324 (to 1116)
            468 LOAD_FAST                7 (item)
            470 LOAD_CONST              15 ('id')
            472 BINARY_SUBSCR
            482 LOAD_FAST                0 (self)
            484 LOAD_ATTR               12 (blacklist)
            494 CONTAINS_OP              1
            496 EXTENDED_ARG             1
            498 POP_JUMP_FORWARD_IF_FALSE   308 (to 1116)

583         500 LOAD_FAST                7 (item)
            502 LOAD_CONST              16 ('price')
            504 BINARY_SUBSCR
            514 LOAD_CONST               2 (0)
            516 COMPARE_OP               4 (>)
            522 POP_JUMP_FORWARD_IF_FALSE     8 (to 540)
            524 LOAD_FAST                0 (self)
            526 LOAD_ATTR               13 (buy_only_free)
            536 POP_JUMP_FORWARD_IF_FALSE     1 (to 540)

584         538 JUMP_BACKWARD           73 (to 394)

586     >>  540 LOAD_FAST                0 (self)
            542 LOAD_ATTR               14 (single_buy)
            552 LOAD_METHOD             15 (get)
            574 PRECALL                  0
            578 CALL                     0
            588 STORE_FAST               8 (d_conn)

587         590 LOAD_FAST                8 (d_conn)
            592 LOAD_METHOD             16 (request)

588         614 LOAD_CONST              17 ('POST')

589         616 LOAD_CONST              18 ('/marketplace-items/v1/items/details')

590         618 LOAD_CONST              19 ('{"itemIds":["%s"]}')
            620 LOAD_FAST                7 (item)
            622 LOAD_CONST              20 ('collectibleItemId')
            624 BINARY_SUBSCR
            634 BINARY_OP                6 (%)

591         638 LOAD_CONST              21 ('application/json')
            640 LOAD_CONST              22 ('.ROBLOSECURITY=%s')
            642 LOAD_FAST                0 (self)
            644 LOAD_ATTR               17 (buyer_cookie)
            654 LOAD_CONST               5 ('cookie')
            656 BINARY_SUBSCR
            666 BINARY_OP                6 (%)
            670 LOAD_FAST                0 (self)
            672 LOAD_ATTR               17 (buyer_cookie)
            682 LOAD_CONST               4 ('auth')
            684 BINARY_SUBSCR
            694 LOAD_CONST              23 (('Content-Type', 'Cookie', 'x-csrf-token'))
            696 BUILD_CONST_KEY_MAP      3

587         698 KW_NAMES                24
            700 PRECALL                  4
            704 CALL                     4
            714 POP_TOP

593         716 LOAD_FAST                8 (d_conn)
            718 LOAD_METHOD             18 (getresponse)
            740 PRECALL                  0
            744 CALL                     0
            754 STORE_FAST               9 (d_resp)

594         756 LOAD_GLOBAL             17 (NULL + json)
            768 LOAD_ATTR               19 (loads)
            778 LOAD_FAST                9 (d_resp)
            780 LOAD_METHOD             20 (read)
            802 PRECALL                  0
            806 CALL                     0
            816 PRECALL                  1
            820 CALL                     1
            830 LOAD_CONST               2 (0)
            832 BINARY_SUBSCR
            842 STORE_FAST              10 (d_data)

595         844 LOAD_FAST                0 (self)
            846 LOAD_ATTR               11 (buyingids)
            856 LOAD_METHOD             21 (append)
            878 LOAD_FAST                7 (item)
            880 LOAD_CONST              15 ('id')
            882 BINARY_SUBSCR
            892 PRECALL                  1
            896 CALL                     1
            906 POP_TOP

596         908 LOAD_FAST                0 (self)
            910 LOAD_ATTR               22 (item_pool)
            920 LOAD_FAST                7 (item)
            922 LOAD_CONST              15 ('id')
            924 BINARY_SUBSCR
            934 BINARY_SUBSCR
            944 GET_ITER
        >>  946 FOR_ITER                51 (to 1050)
            948 STORE_FAST               5 (conn)

597         950 LOAD_GLOBAL             47 (NULL + threading)
            962 LOAD_ATTR               24 (Thread)
            972 LOAD_FAST                0 (self)
            974 LOAD_ATTR               25 (buy_item)
            984 LOAD_FAST                7 (item)
            986 LOAD_FAST                5 (conn)
            988 LOAD_FAST               10 (d_data)
            990 LOAD_CONST              25 ('watcher')
            992 BUILD_TUPLE              4
            994 KW_NAMES                26
            996 PRECALL                  2
           1000 CALL                     2
           1010 LOAD_METHOD             26 (start)
           1032 PRECALL                  0
           1036 CALL                     0
           1046 POP_TOP
           1048 JUMP_BACKWARD           52 (to 946)

598     >> 1050 LOAD_FAST                7 (item)
           1052 LOAD_CONST              16 ('price')
           1054 BINARY_SUBSCR
           1064 LOAD_CONST               2 (0)
           1066 COMPARE_OP               1 (<=)
           1072 POP_JUMP_FORWARD_IF_FALSE    21 (to 1116)

599        1074 LOAD_FAST                0 (self)
           1076 LOAD_METHOD             27 (post_free_item)
           1098 LOAD_FAST                7 (item)
           1100 PRECALL                  1
           1104 CALL                     1
           1114 POP_TOP
        >> 1116 EXTENDED_ARG             1
           1118 JUMP_BACKWARD          363 (to 394)
        >> 1120 JUMP_FORWARD            68 (to 1258)

600     >> 1122 LOAD_FAST                5 (conn)
           1124 LOAD_ATTR                9 (status_code)
           1134 LOAD_CONST              27 (403)
           1136 COMPARE_OP               2 (==)
           1142 POP_JUMP_FORWARD_IF_FALSE    21 (to 1186)

601        1144 LOAD_FAST                0 (self)
           1146 LOAD_METHOD             28 (refresh_tokens)
           1168 PRECALL                  0
           1172 CALL                     0
           1182 POP_TOP
           1184 JUMP_FORWARD            36 (to 1258)

603     >> 1186 LOAD_FAST                0 (self)
           1188 COPY                     1
           1190 LOAD_ATTR               29 (error_count)
           1200 LOAD_CONST              12 (1)
           1202 BINARY_OP               13 (+=)
           1206 SWAP                     2
           1208 STORE_ATTR              29 (error_count)

604        1218 LOAD_GLOBAL             61 (NULL + print)
           1230 LOAD_FAST                5 (conn)
           1232 LOAD_ATTR                9 (status_code)
           1242 PRECALL                  1
           1246 CALL                     1
           1256 POP_TOP

570     >> 1258 LOAD_CONST               0 (None)
           1260 LOAD_CONST               0 (None)
           1262 LOAD_CONST               0 (None)
           1264 PRECALL                  2
           1268 CALL                     2
           1278 POP_TOP
           1280 JUMP_FORWARD            11 (to 1304)
        >> 1282 PUSH_EXC_INFO
           1284 WITH_EXCEPT_START
           1286 POP_JUMP_FORWARD_IF_TRUE     4 (to 1296)
           1288 RERAISE                  2
        >> 1290 COPY                     3
           1292 POP_EXCEPT
           1294 RERAISE                  1
        >> 1296 POP_TOP
           1298 POP_EXCEPT
           1300 POP_TOP
           1302 POP_TOP

605     >> 1304 LOAD_GLOBAL              7 (NULL + time)
           1316 LOAD_ATTR                3 (time)
           1326 PRECALL                  0
           1330 CALL                     0
           1340 STORE_FAST              11 (end_time)

606        1342 LOAD_GLOBAL             63 (NULL + round)
           1354 LOAD_FAST               11 (end_time)
           1356 LOAD_FAST                2 (start_time)
           1358 BINARY_OP               10 (-)
           1362 LOAD_CONST              28 (2)
           1364 PRECALL                  2
           1368 CALL                     2
           1378 LOAD_FAST                0 (self)
           1380 STORE_ATTR              32 (speed_count)
           1390 JUMP_FORWARD            54 (to 1500)
        >> 1392 PUSH_EXC_INFO

607        1394 LOAD_GLOBAL             66 (Exception)
           1406 CHECK_EXC_MATCH
           1408 POP_JUMP_FORWARD_IF_FALSE    41 (to 1492)
           1410 STORE_FAST              12 (error)

608        1412 LOAD_FAST                0 (self)
           1414 COPY                     1
           1416 LOAD_ATTR               29 (error_count)
           1426 LOAD_CONST              12 (1)
           1428 BINARY_OP               13 (+=)
           1432 SWAP                     2
           1434 STORE_ATTR              29 (error_count)

609        1444 LOAD_GLOBAL             61 (NULL + print)
           1456 LOAD_FAST               12 (error)
           1458 PRECALL                  1
           1462 CALL                     1
           1472 POP_TOP

610        1474 POP_EXCEPT
           1476 LOAD_CONST               0 (None)
           1478 STORE_FAST              12 (error)
           1480 DELETE_FAST             12 (error)
           1482 JUMP_FORWARD             8 (to 1500)
        >> 1484 LOAD_CONST               0 (None)
           1486 STORE_FAST              12 (error)
           1488 DELETE_FAST             12 (error)
           1490 RERAISE                  1

607     >> 1492 RERAISE                  0
        >> 1494 COPY                     3
           1496 POP_EXCEPT
           1498 RERAISE                  1

611     >> 1500 LOAD_GLOBAL              7 (NULL + time)
           1512 LOAD_ATTR               34 (sleep)
           1522 LOAD_FAST                0 (self)
           1524 LOAD_ATTR               35 (scan_speed)
           1534 PRECALL                  1
           1538 CALL                     1
           1548 POP_TOP

564        1550 EXTENDED_ARG             3
           1552 JUMP_BACKWARD          768 (to 18)
ExceptionTable:
  70 to 144 -> 1392 [0]
  146 to 1256 -> 1282 [1] lasti
  1258 to 1280 -> 1392 [0]
  1282 to 1288 -> 1290 [3] lasti
  1290 to 1294 -> 1392 [0]
  1296 to 1296 -> 1290 [3] lasti
  1298 to 1388 -> 1392 [0]
  1392 to 1410 -> 1494 [1] lasti
  1412 to 1472 -> 1484 [1] lasti
  1484 to 1492 -> 1494 [1] lasti


----------------------------[END]-------------------------------
